<?xml version="1.0" encoding="utf-8" ?>
<dwsync>
<file name="abacus.svg" server="ftp.mustersite.ch/httpdocs/homepage-maker/" local="131566905265201301" remote="131554039200000000" Dst="1" />
<file name="NewTux.svg" server="ftp.mustersite.ch/httpdocs/homepage-maker/" local="131566905265406859" remote="131554039200000000" Dst="1" />
<file name="address-book.svg" server="ftp.mustersite.ch/httpdocs/homepage-maker/" local="131566905266119061" remote="131554039200000000" Dst="1" />
<file name="address-book2.svg" server="ftp.mustersite.ch/httpdocs/homepage-maker/" local="131566905266353832" remote="131554039200000000" Dst="1" />
<file name="aim.svg" server="ftp.mustersite.ch/httpdocs/homepage-maker/" local="131566905266574402" remote="131554039200000000" Dst="1" />
<file name="alarm.svg" server="ftp.mustersite.ch/httpdocs/homepage-maker/" local="131566905267346934" remote="131554039200000000" Dst="1" />
<file name="apple.svg" server="ftp.mustersite.ch/httpdocs/homepage-maker/" local="131566905267557525" remote="131554039200000000" Dst="1" />
<file name="arrow-left.svg" server="ftp.mustersite.ch/httpdocs/homepage-maker/" local="131566905267793171" remote="131554039200000000" Dst="1" />
<file name="arrow-right.svg" server="ftp.mustersite.ch/httpdocs/homepage-maker/" local="131566905268618108" remote="131554039200000000" Dst="1" />
<file name="arrows-updown.svg" server="ftp.mustersite.ch/httpdocs/homepage-maker/" local="131566905268832095" remote="131554039200000000" Dst="1" />
<file name="atm-cash.svg" server="ftp.mustersite.ch/httpdocs/homepage-maker/" local="131566905269092498" remote="131554039200000000" Dst="1" />
<file name="award1.svg" server="ftp.mustersite.ch/httpdocs/homepage-maker/" local="131566905269999908" remote="131554039200000000" Dst="1" />
<file name="award2.svg" server="ftp.mustersite.ch/httpdocs/homepage-maker/" local="131566905270456127" remote="131554039200000000" Dst="1" />
<file name="award3.svg" server="ftp.mustersite.ch/httpdocs/homepage-maker/" local="131566905270501251" remote="131554039200000000" Dst="1" />
<file name="award4.svg" server="ftp.mustersite.ch/httpdocs/homepage-maker/" local="131566905271415668" remote="131554039200000000" Dst="1" />
<file name="award5.svg" server="ftp.mustersite.ch/httpdocs/homepage-maker/" local="131566905271851826" remote="131554039200000000" Dst="1" />
<file name="badge01.svg" server="ftp.mustersite.ch/httpdocs/homepage-maker/" local="131566905271856842" remote="131554039200000000" Dst="1" />
<file name="badge02.svg" server="ftp.mustersite.ch/httpdocs/homepage-maker/" local="131566905272821128" remote="131554039200000000" Dst="1" />
<file name="bank.svg" server="ftp.mustersite.ch/httpdocs/homepage-maker/" local="131566905273196967" remote="131554039200000000" Dst="1" />
<file name="bank2.svg" server="ftp.mustersite.ch/httpdocs/homepage-maker/" local="131566905273247090" remote="131554039200000000" Dst="1" />
<file name="bell.svg" server="ftp.mustersite.ch/httpdocs/homepage-maker/" local="131566905274489614" remote="131554039200000000" Dst="1" />
<file name="binoculars.svg" server="ftp.mustersite.ch/httpdocs/homepage-maker/" local="131566905274790421" remote="131554039200000000" Dst="1" />
<file name="bomb.svg" server="ftp.mustersite.ch/httpdocs/homepage-maker/" local="131566905274835543" remote="131554039200000000" Dst="1" />
<file name="book-apple.svg" server="ftp.mustersite.ch/httpdocs/homepage-maker/" local="131566905275868056" remote="131554039200000000" Dst="1" />
<file name="book.svg" server="ftp.mustersite.ch/httpdocs/homepage-maker/" local="131566905276193925" remote="131554039200000000" Dst="1" />
<file name="bonsai.svg" server="ftp.mustersite.ch/httpdocs/homepage-maker/" local="131566905276514776" remote="131554039200000000" Dst="1" />
<file name="bookmark.svg" server="ftp.mustersite.ch/httpdocs/homepage-maker/" local="131566905277281827" remote="131554039200000000" Dst="1" />
<file name="box.svg" server="ftp.mustersite.ch/httpdocs/homepage-maker/" local="131566905277572202" remote="131554039200000000" Dst="1" />
<file name="brain.svg" server="ftp.mustersite.ch/httpdocs/homepage-maker/" local="131566905277847536" remote="131554039200000000" Dst="1" />
<file name="briefcase.svg" server="ftp.mustersite.ch/httpdocs/homepage-maker/" local="131566905278736158" remote="131554039200000000" Dst="1" />
<file name="browser01.svg" server="ftp.mustersite.ch/httpdocs/homepage-maker/" local="131566905279893705" remote="131554039200000000" Dst="1" />
<file name="browser02.svg" server="ftp.mustersite.ch/httpdocs/homepage-maker/" local="131566905279943834" remote="131554039200000000" Dst="1" />
<file name="buy-sign.svg" server="ftp.mustersite.ch/httpdocs/homepage-maker/" local="131566905281059997" remote="131554039200000000" Dst="1" />
<file name="calculator1.svg" server="ftp.mustersite.ch/httpdocs/homepage-maker/" local="131566905281260528" remote="131554039200000000" Dst="1" />
<file name="buildings.svg" server="ftp.mustersite.ch/httpdocs/homepage-maker/" local="131566905281496152" remote="131554039200000000" Dst="1" />
<file name="calculator2.svg" server="ftp.mustersite.ch/httpdocs/homepage-maker/" local="131566905282399471" remote="131554039200000000" Dst="1" />
<file name="calculator3.svg" server="ftp.mustersite.ch/httpdocs/homepage-maker/" local="131566905282630081" remote="131554039200000000" Dst="1" />
<file name="calendar1.svg" server="ftp.mustersite.ch/httpdocs/homepage-maker/" local="131566905282845733" remote="131554039200000000" Dst="1" />
<file name="calendar2.svg" server="ftp.mustersite.ch/httpdocs/homepage-maker/" local="131566905283676341" remote="131554039200000000" Dst="1" />
<file name="calendar3.svg" server="ftp.mustersite.ch/httpdocs/homepage-maker/" local="131566905284120008" remote="131554039200000000" Dst="1" />
<file name="calendar4.svg" server="ftp.mustersite.ch/httpdocs/homepage-maker/" local="131566905284185181" remote="131554039200000000" Dst="1" />
<file name="calendar5.svg" server="ftp.mustersite.ch/httpdocs/homepage-maker/" local="131566905285202890" remote="131554039200000000" Dst="1" />
<file name="champagne.svg" server="ftp.mustersite.ch/httpdocs/homepage-maker/" local="131566905285433503" remote="131554039200000000" Dst="1" />
<file name="certificate.svg" server="ftp.mustersite.ch/httpdocs/homepage-maker/" local="131566905285749341" remote="131554039200000000" Dst="1" />
<file name="character01.svg" server="ftp.mustersite.ch/httpdocs/homepage-maker/" local="131566905286471268" remote="131554039200000000" Dst="1" />
<file name="character02.svg" server="ftp.mustersite.ch/httpdocs/homepage-maker/" local="131566905286681832" remote="131554039200000000" Dst="1" />
<file name="character03.svg" server="ftp.mustersite.ch/httpdocs/homepage-maker/" local="131566905287223267" remote="131554039200000000" Dst="1" />
<file name="character04.svg" server="ftp.mustersite.ch/httpdocs/homepage-maker/" local="131566905287704544" remote="131554039200000000" Dst="1" />
<file name="character05.svg" server="ftp.mustersite.ch/httpdocs/homepage-maker/" local="131566905288214474" remote="131554039200000000" Dst="1" />
<file name="character06.svg" server="ftp.mustersite.ch/httpdocs/homepage-maker/" local="131566905288756604" remote="131554039200000000" Dst="1" />
<file name="character07.svg" server="ftp.mustersite.ch/httpdocs/homepage-maker/" local="131566905289764286" remote="131554039200000000" Dst="1" />
<file name="character08.svg" server="ftp.mustersite.ch/httpdocs/homepage-maker/" local="131566905290400970" remote="131554039200000000" Dst="1" />
<file name="chart-analysis.svg" server="ftp.mustersite.ch/httpdocs/homepage-maker/" local="131566905290972498" remote="131554039200000000" Dst="1" />
<file name="chart-board.svg" server="ftp.mustersite.ch/httpdocs/homepage-maker/" local="131566905291238207" remote="131554039200000000" Dst="1" />
<file name="chart-pyramid.svg" server="ftp.mustersite.ch/httpdocs/homepage-maker/" local="131566905291879901" remote="131554039200000000" Dst="1" />
<file name="chart02.svg" server="ftp.mustersite.ch/httpdocs/homepage-maker/" local="131566905292406308" remote="131554039200000000" Dst="1" />
<file name="chart01.svg" server="ftp.mustersite.ch/httpdocs/homepage-maker/" local="131566905292631912" remote="131554039200000000" Dst="1" />
<file name="chart03.svg" server="ftp.mustersite.ch/httpdocs/homepage-maker/" local="131566905293368873" remote="131554039200000000" Dst="1" />
<file name="chart04.svg" server="ftp.mustersite.ch/httpdocs/homepage-maker/" local="131566905293594457" remote="131554039200000000" Dst="1" />
<file name="chart05.svg" server="ftp.mustersite.ch/httpdocs/homepage-maker/" local="131566905293805028" remote="131554039200000000" Dst="1" />
<file name="chart06.svg" server="ftp.mustersite.ch/httpdocs/homepage-maker/" local="131566905294632220" remote="131554039200000000" Dst="1" />
<file name="chart07.svg" server="ftp.mustersite.ch/httpdocs/homepage-maker/" local="131566905294983164" remote="131554039200000000" Dst="1" />
<file name="chart08.svg" server="ftp.mustersite.ch/httpdocs/homepage-maker/" local="131566905295148701" remote="131554039200000000" Dst="1" />
<file name="chart09.svg" server="ftp.mustersite.ch/httpdocs/homepage-maker/" local="131566905296051428" remote="131554039200000000" Dst="1" />
<file name="chart10.svg" server="ftp.mustersite.ch/httpdocs/homepage-maker/" local="131566905296507876" remote="131554039200000000" Dst="1" />
<file name="chart11.svg" server="ftp.mustersite.ch/httpdocs/homepage-maker/" local="131566905296557776" remote="131554039200000000" Dst="1" />
<file name="chart12.svg" server="ftp.mustersite.ch/httpdocs/homepage-maker/" local="131566905297745928" remote="131554039200000000" Dst="1" />
<file name="chart13.svg" server="ftp.mustersite.ch/httpdocs/homepage-maker/" local="131566905298215137" remote="131554039200000000" Dst="1" />
<file name="chart14.svg" server="ftp.mustersite.ch/httpdocs/homepage-maker/" local="131566905298270282" remote="131554039200000000" Dst="1" />
<file name="chart15.svg" server="ftp.mustersite.ch/httpdocs/homepage-maker/" local="131566905299834795" remote="131554039200000000" Dst="1" />
<file name="chart16.svg" server="ftp.mustersite.ch/httpdocs/homepage-maker/" local="131566905300275969" remote="131554039200000000" Dst="1" />
<file name="chart17.svg" server="ftp.mustersite.ch/httpdocs/homepage-maker/" local="131566905300326093" remote="131554039200000000" Dst="1" />
<file name="chart18.svg" server="ftp.mustersite.ch/httpdocs/homepage-maker/" local="131566905301323750" remote="131554039200000000" Dst="1" />
<file name="chart19.svg" server="ftp.mustersite.ch/httpdocs/homepage-maker/" local="131566905301734852" remote="131554039200000000" Dst="1" />
<file name="chart20.svg" server="ftp.mustersite.ch/httpdocs/homepage-maker/" local="131566905301784974" remote="131554039200000000" Dst="1" />
<file name="chart21.svg" server="ftp.mustersite.ch/httpdocs/homepage-maker/" local="131566905302677361" remote="131554039200000000" Dst="1" />
<file name="chat.svg" server="ftp.mustersite.ch/httpdocs/homepage-maker/" local="131566905302902945" remote="131554039200000000" Dst="1" />
<file name="checklist.svg" server="ftp.mustersite.ch/httpdocs/homepage-maker/" local="131566905303168949" remote="131554039200000000" Dst="1" />
<file name="checklist3.svg" server="ftp.mustersite.ch/httpdocs/homepage-maker/" local="131566905304196384" remote="131554039200000000" Dst="1" />
<file name="chemistry.svg" server="ftp.mustersite.ch/httpdocs/homepage-maker/" local="131566905304411965" remote="131554039200000000" Dst="1" />
<file name="checklist2.svg" server="ftp.mustersite.ch/httpdocs/homepage-maker/" local="131566905304702747" remote="131554039200000000" Dst="1" />
<file name="chess-knight.svg" server="ftp.mustersite.ch/httpdocs/homepage-maker/" local="131566905305710416" remote="131554039200000000" Dst="1" />
<file name="chess-rook.svg" server="ftp.mustersite.ch/httpdocs/homepage-maker/" local="131566905306091427" remote="131554039200000000" Dst="1" />
<file name="chess.svg" server="ftp.mustersite.ch/httpdocs/homepage-maker/" local="131566905306156617" remote="131554039200000000" Dst="1" />
<file name="clock.svg" server="ftp.mustersite.ch/httpdocs/homepage-maker/" local="131566905307079085" remote="131554039200000000" Dst="1" />
<file name="closed-sign.svg" server="ftp.mustersite.ch/httpdocs/homepage-maker/" local="131566905307540319" remote="131554039200000000" Dst="1" />
<file name="cloud-coins.svg" server="ftp.mustersite.ch/httpdocs/homepage-maker/" local="131566905307590444" remote="131554039200000000" Dst="1" />
<file name="cloud-down.svg" server="ftp.mustersite.ch/httpdocs/homepage-maker/" local="131566905309356410" remote="131554039200000000" Dst="1" />
<file name="cloud-up.svg" server="ftp.mustersite.ch/httpdocs/homepage-maker/" local="131566905309792563" remote="131554039200000000" Dst="1" />
<file name="coffee.svg" server="ftp.mustersite.ch/httpdocs/homepage-maker/" local="131566905309842697" remote="131554039200000000" Dst="1" />
<file name="coupon.svg" server="ftp.mustersite.ch/httpdocs/homepage-maker/" local="131566905310870432" remote="131554039200000000" Dst="1" />
<file name="conference.svg" server="ftp.mustersite.ch/httpdocs/homepage-maker/" local="131566905311291116" remote="131554039200000000" Dst="1" />
<file name="contact-book.svg" server="ftp.mustersite.ch/httpdocs/homepage-maker/" local="131566905311335960" remote="131554039200000000" Dst="1" />
<file name="credit-card.svg" server="ftp.mustersite.ch/httpdocs/homepage-maker/" local="131566905311947583" remote="131554039200000000" Dst="1" />
<file name="currencies.svg" server="ftp.mustersite.ch/httpdocs/homepage-maker/" local="131566905312429241" remote="131554039200000000" Dst="1" />
<file name="crown.svg" server="ftp.mustersite.ch/httpdocs/homepage-maker/" local="131566905312694949" remote="131554039200000000" Dst="1" />
<file name="database.svg" server="ftp.mustersite.ch/httpdocs/homepage-maker/" local="131566905313276505" remote="131554039200000000" Dst="1" />
<file name="delivery.svg" server="ftp.mustersite.ch/httpdocs/homepage-maker/" local="131566905313543170" remote="131554039200000000" Dst="1" />
<file name="diagram-hierarchy.svg" server="ftp.mustersite.ch/httpdocs/homepage-maker/" local="131566905313934220" remote="131554039200000000" Dst="1" />
<file name="diamond.svg" server="ftp.mustersite.ch/httpdocs/homepage-maker/" local="131566905314500719" remote="131554039200000000" Dst="1" />
<file name="dollar.svg" server="ftp.mustersite.ch/httpdocs/homepage-maker/" local="131566905314901781" remote="131554039200000000" Dst="1" />
<file name="drawer.svg" server="ftp.mustersite.ch/httpdocs/homepage-maker/" local="131566905315388078" remote="131554039200000000" Dst="1" />
<file name="egg.svg" server="ftp.mustersite.ch/httpdocs/homepage-maker/" local="131566905315789145" remote="131554039200000000" Dst="1" />
<file name="emblem.svg" server="ftp.mustersite.ch/httpdocs/homepage-maker/" local="131566905316300504" remote="131554039200000000" Dst="1" />
<file name="envelope-money.svg" server="ftp.mustersite.ch/httpdocs/homepage-maker/" local="131566905316836941" remote="131554039200000000" Dst="1" />
<file name="envelopes.svg" server="ftp.mustersite.ch/httpdocs/homepage-maker/" local="131566905317107652" remote="131554039200000000" Dst="1" />
<file name="euro.svg" server="ftp.mustersite.ch/httpdocs/homepage-maker/" local="131566905317558861" remote="131554039200000000" Dst="1" />
<file name="exchange.svg" server="ftp.mustersite.ch/httpdocs/homepage-maker/" local="131566905319239620" remote="131554039200000000" Dst="1" />
<file name="exit.svg" server="ftp.mustersite.ch/httpdocs/homepage-maker/" local="131566905319450171" remote="131554039200000000" Dst="1" />
<file name="factory.svg" server="ftp.mustersite.ch/httpdocs/homepage-maker/" local="131566905319851523" remote="131554039200000000" Dst="1" />
<file name="fax.svg" server="ftp.mustersite.ch/httpdocs/homepage-maker/" local="131566905320623641" remote="131554039200000000" Dst="1" />
<file name="file01.svg" server="ftp.mustersite.ch/httpdocs/homepage-maker/" local="131566905320818662" remote="131554039200000000" Dst="1" />
<file name="file02.svg" server="ftp.mustersite.ch/httpdocs/homepage-maker/" local="131566905321289907" remote="131554039200000000" Dst="1" />
<file name="file03.svg" server="ftp.mustersite.ch/httpdocs/homepage-maker/" local="131566905321910614" remote="131554039200000000" Dst="1" />
<file name="file04.svg" server="ftp.mustersite.ch/httpdocs/homepage-maker/" local="131566905322904647" remote="131554039200000000" Dst="1" />
<file name="file05.svg" server="ftp.mustersite.ch/httpdocs/homepage-maker/" local="131566905323122944" remote="131554039200000000" Dst="1" />
<file name="file06.svg" server="ftp.mustersite.ch/httpdocs/homepage-maker/" local="131566905323715987" remote="131554039200000000" Dst="1" />
<file name="file07.svg" server="ftp.mustersite.ch/httpdocs/homepage-maker/" local="131566905324110963" remote="131554039200000000" Dst="1" />
<file name="file08.svg" server="ftp.mustersite.ch/httpdocs/homepage-maker/" local="131566905324607274" remote="131554039200000000" Dst="1" />
<file name="file09.svg" server="ftp.mustersite.ch/httpdocs/homepage-maker/" local="131566905325088558" remote="131554039200000000" Dst="1" />
<file name="file10.svg" server="ftp.mustersite.ch/httpdocs/homepage-maker/" local="131566905325559808" remote="131554039200000000" Dst="1" />
<file name="files.svg" server="ftp.mustersite.ch/httpdocs/homepage-maker/" local="131566905326026082" remote="131554039200000000" Dst="1" />
<file name="fire.svg" server="ftp.mustersite.ch/httpdocs/homepage-maker/" local="131566905326297537" remote="131554039200000000" Dst="1" />
<file name="fish.svg" server="ftp.mustersite.ch/httpdocs/homepage-maker/" local="131566905326929218" remote="131554039200000000" Dst="1" />
<file name="flag.svg" server="ftp.mustersite.ch/httpdocs/homepage-maker/" local="131566905327209972" remote="131554039200000000" Dst="1" />
<file name="folder-add.svg" server="ftp.mustersite.ch/httpdocs/homepage-maker/" local="131566905327616053" remote="131554039200000000" Dst="1" />
<file name="folder-online.svg" server="ftp.mustersite.ch/httpdocs/homepage-maker/" local="131566905329287799" remote="131554039200000000" Dst="1" />
<file name="folder-delete.svg" server="ftp.mustersite.ch/httpdocs/homepage-maker/" local="131566905329548192" remote="131554039200000000" Dst="1" />
<file name="folder-private.svg" server="ftp.mustersite.ch/httpdocs/homepage-maker/" local="131566905329738700" remote="131554039200000000" Dst="1" />
<file name="folder-remove.svg" server="ftp.mustersite.ch/httpdocs/homepage-maker/" local="131566905330525793" remote="131554039200000000" Dst="1" />
<file name="folder.svg" server="ftp.mustersite.ch/httpdocs/homepage-maker/" local="131566905330766433" remote="131554039200000000" Dst="1" />
<file name="folders.svg" server="ftp.mustersite.ch/httpdocs/homepage-maker/" local="131566905331062223" remote="131554039200000000" Dst="1" />
<file name="funnel-money.svg" server="ftp.mustersite.ch/httpdocs/homepage-maker/" local="131566905331734008" remote="131554039200000000" Dst="1" />
<file name="funnel.svg" server="ftp.mustersite.ch/httpdocs/homepage-maker/" local="131566905332059713" remote="131554039200000000" Dst="1" />
<file name="gauge.svg" server="ftp.mustersite.ch/httpdocs/homepage-maker/" local="131566905332320406" remote="131554039200000000" Dst="1" />
<file name="gauge2.svg" server="ftp.mustersite.ch/httpdocs/homepage-maker/" local="131566905333107501" remote="131554039200000000" Dst="1" />
<file name="gears1.svg" server="ftp.mustersite.ch/httpdocs/homepage-maker/" local="131566905333463449" remote="131554039200000000" Dst="1" />
<file name="gears2.svg" server="ftp.mustersite.ch/httpdocs/homepage-maker/" local="131566905333764246" remote="131554039200000000" Dst="1" />
<file name="glasses-moustache.svg" server="ftp.mustersite.ch/httpdocs/homepage-maker/" local="131566905334273040" remote="131554039200000000" Dst="1" />
<file name="globe-money.svg" server="ftp.mustersite.ch/httpdocs/homepage-maker/" local="131566905334804455" remote="131554039200000000" Dst="1" />
<file name="globe.svg" server="ftp.mustersite.ch/httpdocs/homepage-maker/" local="131566905335000285" remote="131554039200000000" Dst="1" />
<file name="globe2.svg" server="ftp.mustersite.ch/httpdocs/homepage-maker/" local="131566905335614980" remote="131554039200000000" Dst="1" />
<file name="graduation-hat.svg" server="ftp.mustersite.ch/httpdocs/homepage-maker/" local="131566905336146848" remote="131554039200000000" Dst="1" />
<file name="hand-globe.svg" server="ftp.mustersite.ch/httpdocs/homepage-maker/" local="131566905336386988" remote="131554039200000000" Dst="1" />
<file name="hand-key.svg" server="ftp.mustersite.ch/httpdocs/homepage-maker/" local="131566905336838465" remote="131554039200000000" Dst="1" />
<file name="hand-money.svg" server="ftp.mustersite.ch/httpdocs/homepage-maker/" local="131566905338442843" remote="131554039200000000" Dst="1" />
<file name="hand-money2.svg" server="ftp.mustersite.ch/httpdocs/homepage-maker/" local="131566905338838617" remote="131554039200000000" Dst="1" />
<file name="handshake.svg" server="ftp.mustersite.ch/httpdocs/homepage-maker/" local="131566905339374846" remote="131554039200000000" Dst="1" />
<file name="hat-moustache.svg" server="ftp.mustersite.ch/httpdocs/homepage-maker/" local="131566905340046629" remote="131554039200000000" Dst="1" />
<file name="hat.svg" server="ftp.mustersite.ch/httpdocs/homepage-maker/" local="131566905340287279" remote="131554039200000000" Dst="1" />
<file name="head-arrows.svg" server="ftp.mustersite.ch/httpdocs/homepage-maker/" local="131566905340748764" remote="131554039200000000" Dst="1" />
<file name="head-battery.svg" server="ftp.mustersite.ch/httpdocs/homepage-maker/" local="131566905341189674" remote="131554039200000000" Dst="1" />
<file name="head-check.svg" server="ftp.mustersite.ch/httpdocs/homepage-maker/" local="131566905341435324" remote="131554039200000000" Dst="1" />
<file name="head-compass.svg" server="ftp.mustersite.ch/httpdocs/homepage-maker/" local="131566905341896551" remote="131554039200000000" Dst="1" />
<file name="head-dollar.svg" server="ftp.mustersite.ch/httpdocs/homepage-maker/" local="131566905342599883" remote="131554039200000000" Dst="1" />
<file name="head-exclamation.svg" server="ftp.mustersite.ch/httpdocs/homepage-maker/" local="131566905342780363" remote="131554039200000000" Dst="1" />
<file name="head-flash.svg" server="ftp.mustersite.ch/httpdocs/homepage-maker/" local="131566905343321803" remote="131554039200000000" Dst="1" />
<file name="head-gauge.svg" server="ftp.mustersite.ch/httpdocs/homepage-maker/" local="131566905343953740" remote="131554039200000000" Dst="1" />
<file name="head-gears.svg" server="ftp.mustersite.ch/httpdocs/homepage-maker/" local="131566905344189647" remote="131554039200000000" Dst="1" />
<file name="head-hourglass.svg" server="ftp.mustersite.ch/httpdocs/homepage-maker/" local="131566905344665642" remote="131554039200000000" Dst="1" />
<file name="head-idea.svg" server="ftp.mustersite.ch/httpdocs/homepage-maker/" local="131566905345301831" remote="131554039200000000" Dst="1" />
<file name="head-question.svg" server="ftp.mustersite.ch/httpdocs/homepage-maker/" local="131566905345527142" remote="131554039200000000" Dst="1" />
<file name="head-structure.svg" server="ftp.mustersite.ch/httpdocs/homepage-maker/" local="131566905346023468" remote="131554039200000000" Dst="1" />
<file name="head.svg" server="ftp.mustersite.ch/httpdocs/homepage-maker/" local="131566905346667581" remote="131554039200000000" Dst="1" />
<file name="headquarters.svg" server="ftp.mustersite.ch/httpdocs/homepage-maker/" local="131566905346883152" remote="131554039200000000" Dst="1" />
<file name="hourglass.svg" server="ftp.mustersite.ch/httpdocs/homepage-maker/" local="131566905348424938" remote="131554039200000000" Dst="1" />
<file name="hours.svg" server="ftp.mustersite.ch/httpdocs/homepage-maker/" local="131566905348936533" remote="131554039200000000" Dst="1" />
<file name="incoming.svg" server="ftp.mustersite.ch/httpdocs/homepage-maker/" local="131566905349217041" remote="131554039200000000" Dst="1" />
<file name="ingots.svg" server="ftp.mustersite.ch/httpdocs/homepage-maker/" local="131566905349723662" remote="131554039200000000" Dst="1" />
<file name="key2.svg" server="ftp.mustersite.ch/httpdocs/homepage-maker/" local="131566905350445553" remote="131554039200000000" Dst="1" />
<file name="key.svg" server="ftp.mustersite.ch/httpdocs/homepage-maker/" local="131566905350625796" remote="131554039200000000" Dst="1" />
<file name="keyboard.svg" server="ftp.mustersite.ch/httpdocs/homepage-maker/" local="131566905351267781" remote="131554039200000000" Dst="1" />
<file name="label.svg" server="ftp.mustersite.ch/httpdocs/homepage-maker/" local="131566905351793361" remote="131554039200000000" Dst="1" />
<file name="lamp.svg" server="ftp.mustersite.ch/httpdocs/homepage-maker/" local="131566905351993887" remote="131554039200000000" Dst="1" />
<file name="laptop-article.svg" server="ftp.mustersite.ch/httpdocs/homepage-maker/" local="131566905352600504" remote="131554039200000000" Dst="1" />
<file name="laptop-chart.svg" server="ftp.mustersite.ch/httpdocs/homepage-maker/" local="131566905353105570" remote="131554039200000000" Dst="1" />
<file name="laptop-cart.svg" server="ftp.mustersite.ch/httpdocs/homepage-maker/" local="131566905353346220" remote="131554039200000000" Dst="1" />
<file name="laptop-chart2.svg" server="ftp.mustersite.ch/httpdocs/homepage-maker/" local="131566905353767333" remote="131554039200000000" Dst="1" />
<file name="laptop-diagram.svg" server="ftp.mustersite.ch/httpdocs/homepage-maker/" local="131566905354308261" remote="131554039200000000" Dst="1" />
<file name="laptop-envelope.svg" server="ftp.mustersite.ch/httpdocs/homepage-maker/" local="131566905354623387" remote="131554039200000000" Dst="1" />
<file name="laptop-finance.svg" server="ftp.mustersite.ch/httpdocs/homepage-maker/" local="131566905355118296" remote="131554039200000000" Dst="1" />
<file name="laptop-privacy.svg" server="ftp.mustersite.ch/httpdocs/homepage-maker/" local="131566905355597959" remote="131554039200000000" Dst="1" />
<file name="laptop-settings.svg" server="ftp.mustersite.ch/httpdocs/homepage-maker/" local="131566905356027354" remote="131554039200000000" Dst="1" />
<file name="laptop-user.svg" server="ftp.mustersite.ch/httpdocs/homepage-maker/" local="131566905356508229" remote="131554039200000000" Dst="1" />
<file name="laptop.svg" server="ftp.mustersite.ch/httpdocs/homepage-maker/" local="131566905356894255" remote="131554039200000000" Dst="1" />
<file name="lightbulb-green.svg" server="ftp.mustersite.ch/httpdocs/homepage-maker/" local="131566905363623717" remote="131554039200000000" Dst="1" />
<file name="lightbulb.svg" server="ftp.mustersite.ch/httpdocs/homepage-maker/" local="131566905364082888" remote="131554039200000000" Dst="1" />
<file name="lightning.svg" server="ftp.mustersite.ch/httpdocs/homepage-maker/" local="131566905364363354" remote="131554039200000000" Dst="1" />
<file name="like.svg" server="ftp.mustersite.ch/httpdocs/homepage-maker/" local="131566905364904785" remote="131554039200000000" Dst="1" />
<file name="lock.svg" server="ftp.mustersite.ch/httpdocs/homepage-maker/" local="131566905365386223" remote="131554039200000000" Dst="1" />
<file name="magnet-money.svg" server="ftp.mustersite.ch/httpdocs/homepage-maker/" local="131566905365702066" remote="131554039200000000" Dst="1" />
<file name="magnifying-glass.svg" server="ftp.mustersite.ch/httpdocs/homepage-maker/" local="131566905366277703" remote="131554039200000000" Dst="1" />
<file name="manager-globe.svg" server="ftp.mustersite.ch/httpdocs/homepage-maker/" local="131566905366859254" remote="131554039200000000" Dst="1" />
<file name="manager-idea.svg" server="ftp.mustersite.ch/httpdocs/homepage-maker/" local="131566905368067467" remote="131554039200000000" Dst="1" />
<file name="manager01.svg" server="ftp.mustersite.ch/httpdocs/homepage-maker/" local="131566905368683542" remote="131554039200000000" Dst="1" />
<file name="manager02.svg" server="ftp.mustersite.ch/httpdocs/homepage-maker/" local="131566905369192782" remote="131554039200000000" Dst="1" />
<file name="meditation.svg" server="ftp.mustersite.ch/httpdocs/homepage-maker/" local="131566905369393315" remote="131554039200000000" Dst="1" />
<file name="megaphone.svg" server="ftp.mustersite.ch/httpdocs/homepage-maker/" local="131566905370141881" remote="131554039200000000" Dst="1" />
<file name="money-scales.svg" server="ftp.mustersite.ch/httpdocs/homepage-maker/" local="131566905370708394" remote="131554039200000000" Dst="1" />
<file name="money-growth.svg" server="ftp.mustersite.ch/httpdocs/homepage-maker/" local="131566905370933993" remote="131554039200000000" Dst="1" />
<file name="money.svg" server="ftp.mustersite.ch/httpdocs/homepage-maker/" local="131566905371555642" remote="131554039200000000" Dst="1" />
<file name="money2.svg" server="ftp.mustersite.ch/httpdocs/homepage-maker/" local="131566905371766198" remote="131554039200000000" Dst="1" />
<file name="money3.svg" server="ftp.mustersite.ch/httpdocs/homepage-maker/" local="131566905372182315" remote="131554039200000000" Dst="1" />
<file name="money4.svg" server="ftp.mustersite.ch/httpdocs/homepage-maker/" local="131566905372758474" remote="131554039200000000" Dst="1" />
<file name="money5.svg" server="ftp.mustersite.ch/httpdocs/homepage-maker/" local="131566905373029204" remote="131554039200000000" Dst="1" />
<file name="money6.svg" server="ftp.mustersite.ch/httpdocs/homepage-maker/" local="131566905373415152" remote="131554039200000000" Dst="1" />
<file name="monitor.svg" server="ftp.mustersite.ch/httpdocs/homepage-maker/" local="131566905374103059" remote="131554039200000000" Dst="1" />
<file name="mouse.svg" server="ftp.mustersite.ch/httpdocs/homepage-maker/" local="131566905374303350" remote="131554039200000000" Dst="1" />
<file name="nest-money.svg" server="ftp.mustersite.ch/httpdocs/homepage-maker/" local="131566905374873321" remote="131554039200000000" Dst="1" />
<file name="newspaper-pen.svg" server="ftp.mustersite.ch/httpdocs/homepage-maker/" local="131566905375392274" remote="131554039200000000" Dst="1" />
<file name="newspaper-jobs.svg" server="ftp.mustersite.ch/httpdocs/homepage-maker/" local="131566905375652975" remote="131554039200000000" Dst="1" />
<file name="newspaper.svg" server="ftp.mustersite.ch/httpdocs/homepage-maker/" local="131566905376275635" remote="131554039200000000" Dst="1" />
<file name="note-paper.svg" server="ftp.mustersite.ch/httpdocs/homepage-maker/" local="131566905376761923" remote="131554039200000000" Dst="1" />
<file name="office-chair.svg" server="ftp.mustersite.ch/httpdocs/homepage-maker/" local="131566905377027644" remote="131554039200000000" Dst="1" />
<file name="open-sign.svg" server="ftp.mustersite.ch/httpdocs/homepage-maker/" local="131566905377727155" remote="131554039200000000" Dst="1" />
<file name="outgoing.svg" server="ftp.mustersite.ch/httpdocs/homepage-maker/" local="131566905378503593" remote="131554039200000000" Dst="1" />
<file name="paper-clip.svg" server="ftp.mustersite.ch/httpdocs/homepage-maker/" local="131566905378723117" remote="131554039200000000" Dst="1" />
<file name="paper-plane.svg" server="ftp.mustersite.ch/httpdocs/homepage-maker/" local="131566905379417654" remote="131554039200000000" Dst="1" />
<file name="pen.svg" server="ftp.mustersite.ch/httpdocs/homepage-maker/" local="131566905379658294" remote="131554039200000000" Dst="1" />
<file name="pen2.svg" server="ftp.mustersite.ch/httpdocs/homepage-maker/" local="131566905379924013" remote="131554039200000000" Dst="1" />
<file name="pencil.svg" server="ftp.mustersite.ch/httpdocs/homepage-maker/" local="131566905380634278" remote="131554039200000000" Dst="1" />
<file name="pens-pencils.svg" server="ftp.mustersite.ch/httpdocs/homepage-maker/" local="131566905380995543" remote="131554039200000000" Dst="1" />
<file name="people-arrows06.svg" server="ftp.mustersite.ch/httpdocs/homepage-maker/" local="131566905381211098" remote="131554039200000000" Dst="1" />
<file name="people-gears.svg" server="ftp.mustersite.ch/httpdocs/homepage-maker/" local="131566905382188744" remote="131554039200000000" Dst="1" />
<file name="people-idea.svg" server="ftp.mustersite.ch/httpdocs/homepage-maker/" local="131566905382594824" remote="131554039200000000" Dst="1" />
<file name="people-handshake.svg" server="ftp.mustersite.ch/httpdocs/homepage-maker/" local="131566905382820426" remote="131554039200000000" Dst="1" />
<file name="people-meeting.svg" server="ftp.mustersite.ch/httpdocs/homepage-maker/" local="131566905383699159" remote="131554039200000000" Dst="1" />
<file name="people-meeting02.svg" server="ftp.mustersite.ch/httpdocs/homepage-maker/" local="131566905383929771" remote="131554039200000000" Dst="1" />
<file name="people-search01.svg" server="ftp.mustersite.ch/httpdocs/homepage-maker/" local="131566905384195492" remote="131554039200000000" Dst="1" />
<file name="people-structure.svg" server="ftp.mustersite.ch/httpdocs/homepage-maker/" local="131566905385042730" remote="131554039200000000" Dst="1" />
<file name="people-search02.svg" server="ftp.mustersite.ch/httpdocs/homepage-maker/" local="131566905385268329" remote="131554039200000000" Dst="1" />
<file name="people-structure01.svg" server="ftp.mustersite.ch/httpdocs/homepage-maker/" local="131566905385478905" remote="131554039200000000" Dst="1" />
<file name="people-structure02.svg" server="ftp.mustersite.ch/httpdocs/homepage-maker/" local="131566905386070060" remote="131554039200000000" Dst="1" />
<file name="people-structure04.svg" server="ftp.mustersite.ch/httpdocs/homepage-maker/" local="131566905387267935" remote="131554039200000000" Dst="1" />
<file name="people-structure03.svg" server="ftp.mustersite.ch/httpdocs/homepage-maker/" local="131566905387518305" remote="131554039200000000" Dst="1" />
<file name="people-structure05.svg" server="ftp.mustersite.ch/httpdocs/homepage-maker/" local="131566905387944692" remote="131554039200000000" Dst="1" />
<file name="people-structure06.svg" server="ftp.mustersite.ch/httpdocs/homepage-maker/" local="131566905388571384" remote="131554039200000000" Dst="1" />
<file name="people-structure07.svg" server="ftp.mustersite.ch/httpdocs/homepage-maker/" local="131566905388807002" remote="131554039200000000" Dst="1" />
<file name="percent.svg" server="ftp.mustersite.ch/httpdocs/homepage-maker/" local="131566905389282079" remote="131554039200000000" Dst="1" />
<file name="periscopemoney.svg" server="ftp.mustersite.ch/httpdocs/homepage-maker/" local="131566905389969178" remote="131554039200000000" Dst="1" />
<file name="person-arrows01.svg" server="ftp.mustersite.ch/httpdocs/homepage-maker/" local="131566905390174449" remote="131554039200000000" Dst="1" />
<file name="person-arrows012.svg" server="ftp.mustersite.ch/httpdocs/homepage-maker/" local="131566905390841229" remote="131554039200000000" Dst="1" />
<file name="person-arrows02.svg" server="ftp.mustersite.ch/httpdocs/homepage-maker/" local="131566905391347575" remote="131554039200000000" Dst="1" />
<file name="person-arrows022.svg" server="ftp.mustersite.ch/httpdocs/homepage-maker/" local="131566905391633327" remote="131554039200000000" Dst="1" />
<file name="person-arrows03.svg" server="ftp.mustersite.ch/httpdocs/homepage-maker/" local="131566905392352087" remote="131554039200000000" Dst="1" />
<file name="person-cross.svg" server="ftp.mustersite.ch/httpdocs/homepage-maker/" local="131566905392818326" remote="131554039200000000" Dst="1" />
<file name="person-checkmark.svg" server="ftp.mustersite.ch/httpdocs/homepage-maker/" local="131566905393058966" remote="131554039200000000" Dst="1" />
<file name="person-data.svg" server="ftp.mustersite.ch/httpdocs/homepage-maker/" local="131566905393740787" remote="131554039200000000" Dst="1" />
<file name="person-dollar.svg" server="ftp.mustersite.ch/httpdocs/homepage-maker/" local="131566905394222072" remote="131554039200000000" Dst="1" />
<file name="person-finance.svg" server="ftp.mustersite.ch/httpdocs/homepage-maker/" local="131566905394452684" remote="131554039200000000" Dst="1" />
<file name="person-flag.svg" server="ftp.mustersite.ch/httpdocs/homepage-maker/" local="131566905395104406" remote="131554039200000000" Dst="1" />
<file name="person-globe.svg" server="ftp.mustersite.ch/httpdocs/homepage-maker/" local="131566905395475396" remote="131554039200000000" Dst="1" />
<file name="person-idea02.svg" server="ftp.mustersite.ch/httpdocs/homepage-maker/" local="131566905395716034" remote="131554039200000000" Dst="1" />
<file name="person-scales.svg" server="ftp.mustersite.ch/httpdocs/homepage-maker/" local="131566905397496048" remote="131554039200000000" Dst="1" />
<file name="person-info.svg" server="ftp.mustersite.ch/httpdocs/homepage-maker/" local="131566905397726655" remote="131554039200000000" Dst="1" />
<file name="person-puzzle.svg" server="ftp.mustersite.ch/httpdocs/homepage-maker/" local="131566905397922176" remote="131554039200000000" Dst="1" />
<file name="person-time.svg" server="ftp.mustersite.ch/httpdocs/homepage-maker/" local="131566905398764423" remote="131554039200000000" Dst="1" />
<file name="person-umbrella.svg" server="ftp.mustersite.ch/httpdocs/homepage-maker/" local="131566905399020101" remote="131554039200000000" Dst="1" />
<file name="phone.svg" server="ftp.mustersite.ch/httpdocs/homepage-maker/" local="131566905399235668" remote="131554039200000000" Dst="1" />
<file name="pie-chart01.svg" server="ftp.mustersite.ch/httpdocs/homepage-maker/" local="131566905400012740" remote="131554039200000000" Dst="1" />
<file name="piggy-bank.svg" server="ftp.mustersite.ch/httpdocs/homepage-maker/" local="131566905400278443" remote="131554039200000000" Dst="1" />
<file name="pie-chart02.svg" server="ftp.mustersite.ch/httpdocs/homepage-maker/" local="131566905400564212" remote="131554039200000000" Dst="1" />
<file name="pin.svg" server="ftp.mustersite.ch/httpdocs/homepage-maker/" local="131566905401065534" remote="131554039200000000" Dst="1" />
<file name="plant-money.svg" server="ftp.mustersite.ch/httpdocs/homepage-maker/" local="131566905401341270" remote="131554039200000000" Dst="1" />
<file name="plant.svg" server="ftp.mustersite.ch/httpdocs/homepage-maker/" local="131566905401872684" remote="131554039200000000" Dst="1" />
<file name="pound.svg" server="ftp.mustersite.ch/httpdocs/homepage-maker/" local="131566905402427217" remote="131554039200000000" Dst="1" />
<file name="presentation.svg" server="ftp.mustersite.ch/httpdocs/homepage-maker/" local="131566905402923535" remote="131554039200000000" Dst="1" />
<file name="presentation02.svg" server="ftp.mustersite.ch/httpdocs/homepage-maker/" local="131566905403374739" remote="131554039200000000" Dst="1" />
<file name="preson-chart02.svg" server="ftp.mustersite.ch/httpdocs/homepage-maker/" local="131566905403690589" remote="131554039200000000" Dst="1" />
<file name="preson-chart03.svg" server="ftp.mustersite.ch/httpdocs/homepage-maker/" local="131566905404201935" remote="131554039200000000" Dst="1" />
<file name="preson-chart04.svg" server="ftp.mustersite.ch/httpdocs/homepage-maker/" local="131566905404648246" remote="131554039200000000" Dst="1" />
<file name="preson-laurels.svg" server="ftp.mustersite.ch/httpdocs/homepage-maker/" local="131566905404928985" remote="131554039200000000" Dst="1" />
<file name="preson-megaphone.svg" server="ftp.mustersite.ch/httpdocs/homepage-maker/" local="131566905405796313" remote="131554039200000000" Dst="1" />
<file name="printer.svg" server="ftp.mustersite.ch/httpdocs/homepage-maker/" local="131566905407172098" remote="131554039200000000" Dst="1" />
<file name="preson-stairs.svg" server="ftp.mustersite.ch/httpdocs/homepage-maker/" local="131566905407402715" remote="131554039200000000" Dst="1" />
<file name="profile.svg" server="ftp.mustersite.ch/httpdocs/homepage-maker/" local="131566905407989275" remote="131554039200000000" Dst="1" />
<file name="pulse.svg" server="ftp.mustersite.ch/httpdocs/homepage-maker/" local="131566905408295102" remote="131554039200000000" Dst="1" />
<file name="puzzle.svg" server="ftp.mustersite.ch/httpdocs/homepage-maker/" local="131566905408796423" remote="131554039200000000" Dst="1" />
<file name="quill.svg" server="ftp.mustersite.ch/httpdocs/homepage-maker/" local="131566905409352901" remote="131554039200000000" Dst="1" />
<file name="recycle.svg" server="ftp.mustersite.ch/httpdocs/homepage-maker/" local="131566905409593543" remote="131554039200000000" Dst="1" />
<file name="rocket.svg" server="ftp.mustersite.ch/httpdocs/homepage-maker/" local="131566905410450822" remote="131554039200000000" Dst="1" />
<file name="rocket2.svg" server="ftp.mustersite.ch/httpdocs/homepage-maker/" local="131566905410666395" remote="131554039200000000" Dst="1" />
<file name="ruble.svg" server="ftp.mustersite.ch/httpdocs/homepage-maker/" local="131566905411127622" remote="131554039200000000" Dst="1" />
<file name="safe.svg" server="ftp.mustersite.ch/httpdocs/homepage-maker/" local="131566905411759391" remote="131554039200000000" Dst="1" />
<file name="ruler-compasses.svg" server="ftp.mustersite.ch/httpdocs/homepage-maker/" local="131566905411979978" remote="131554039200000000" Dst="1" />
<file name="sale-sign.svg" server="ftp.mustersite.ch/httpdocs/homepage-maker/" local="131566905412476298" remote="131554039200000000" Dst="1" />
<file name="satellite-dish.svg" server="ftp.mustersite.ch/httpdocs/homepage-maker/" local="131566905412907756" remote="131554039200000000" Dst="1" />
<file name="scales.svg" server="ftp.mustersite.ch/httpdocs/homepage-maker/" local="131566905413153096" remote="131554039200000000" Dst="1" />
<file name="scissors.svg" server="ftp.mustersite.ch/httpdocs/homepage-maker/" local="131566905413832445" remote="131554039200000000" Dst="1" />
<file name="security.svg" server="ftp.mustersite.ch/httpdocs/homepage-maker/" local="131566905414498781" remote="131554039200000000" Dst="1" />
<file name="send.svg" server="ftp.mustersite.ch/httpdocs/homepage-maker/" local="131566905414744443" remote="131554039200000000" Dst="1" />
<file name="shield.svg" server="ftp.mustersite.ch/httpdocs/homepage-maker/" local="131566905415265835" remote="131554039200000000" Dst="1" />
<file name="shopping-cart.svg" server="ftp.mustersite.ch/httpdocs/homepage-maker/" local="131566905416692349" remote="131554039200000000" Dst="1" />
<file name="sign.svg" server="ftp.mustersite.ch/httpdocs/homepage-maker/" local="131566905416938002" remote="131554039200000000" Dst="1" />
<file name="smartphone-chart.svg" server="ftp.mustersite.ch/httpdocs/homepage-maker/" local="131566905417499495" remote="131554039200000000" Dst="1" />
<file name="smartphone-exclamation.svg" server="ftp.mustersite.ch/httpdocs/homepage-maker/" local="131566905418060994" remote="131554039200000000" Dst="1" />
<file name="smartphone-gears.svg" server="ftp.mustersite.ch/httpdocs/homepage-maker/" local="131566905418306644" remote="131554039200000000" Dst="1" />
<file name="smartphone-growth.svg" server="ftp.mustersite.ch/httpdocs/homepage-maker/" local="131566905418868135" remote="131554039200000000" Dst="1" />
<file name="smartphone-money.svg" server="ftp.mustersite.ch/httpdocs/homepage-maker/" local="131566905419289257" remote="131554039200000000" Dst="1" />
<file name="smartphone-user.svg" server="ftp.mustersite.ch/httpdocs/homepage-maker/" local="131566905419489790" remote="131554039200000000" Dst="1" />
<file name="smartphone.svg" server="ftp.mustersite.ch/httpdocs/homepage-maker/" local="131566905420386290" remote="131554039200000000" Dst="1" />
<file name="speaker02.svg" server="ftp.mustersite.ch/httpdocs/homepage-maker/" local="131566905420636951" remote="131554039200000000" Dst="1" />
<file name="speaker.svg" server="ftp.mustersite.ch/httpdocs/homepage-maker/" local="131566905420857532" remote="131554039200000000" Dst="1" />
<file name="speech-bubble.svg" server="ftp.mustersite.ch/httpdocs/homepage-maker/" local="131566905421734874" remote="131554039200000000" Dst="1" />
<file name="stamp.svg" server="ftp.mustersite.ch/httpdocs/homepage-maker/" local="131566905422010610" remote="131554039200000000" Dst="1" />
<file name="star.svg" server="ftp.mustersite.ch/httpdocs/homepage-maker/" local="131566905422251238" remote="131554039200000000" Dst="1" />
<file name="steering-wheel.svg" server="ftp.mustersite.ch/httpdocs/homepage-maker/" local="131566905423312131" remote="131554039200000000" Dst="1" />
<file name="strategy03.svg" server="ftp.mustersite.ch/httpdocs/homepage-maker/" local="131566905423704396" remote="131554039200000000" Dst="1" />
<file name="strategy1.svg" server="ftp.mustersite.ch/httpdocs/homepage-maker/" local="131566905423749525" remote="131554039200000000" Dst="1" />
<file name="strategy2.svg" server="ftp.mustersite.ch/httpdocs/homepage-maker/" local="131566905424725763" remote="131554039200000000" Dst="1" />
<file name="support-person.svg" server="ftp.mustersite.ch/httpdocs/homepage-maker/" local="131566905425097021" remote="131554039200000000" Dst="1" />
<file name="tablet-article.svg" server="ftp.mustersite.ch/httpdocs/homepage-maker/" local="131566905425136989" remote="131554039200000000" Dst="1" />
<file name="tablet-chart.svg" server="ftp.mustersite.ch/httpdocs/homepage-maker/" local="131566905426801040" remote="131554039200000000" Dst="1" />
<file name="tablet-chart2.svg" server="ftp.mustersite.ch/httpdocs/homepage-maker/" local="131566905427191940" remote="131554039200000000" Dst="1" />
<file name="tablet-chart3.svg" server="ftp.mustersite.ch/httpdocs/homepage-maker/" local="131566905427252097" remote="131554039200000000" Dst="1" />
<file name="tablet-pie-chart.svg" server="ftp.mustersite.ch/httpdocs/homepage-maker/" local="131566905428271838" remote="131554039200000000" Dst="1" />
<file name="tablet-pie-chart2.svg" server="ftp.mustersite.ch/httpdocs/homepage-maker/" local="131566905428718275" remote="131554039200000000" Dst="1" />
<file name="tablet.svg" server="ftp.mustersite.ch/httpdocs/homepage-maker/" local="131566905428778181" remote="131554039200000000" Dst="1" />
<file name="target.svg" server="ftp.mustersite.ch/httpdocs/homepage-maker/" local="131566905429751422" remote="131554039200000000" Dst="1" />
<file name="team.svg" server="ftp.mustersite.ch/httpdocs/homepage-maker/" local="131566905430097083" remote="131554039200000000" Dst="1" />
<file name="telescope.svg" server="ftp.mustersite.ch/httpdocs/homepage-maker/" local="131566905430162258" remote="131554039200000000" Dst="1" />
<file name="tie.svg" server="ftp.mustersite.ch/httpdocs/homepage-maker/" local="131566905431029562" remote="131554039200000000" Dst="1" />
<file name="tools.svg" server="ftp.mustersite.ch/httpdocs/homepage-maker/" local="131566905431320324" remote="131554039200000000" Dst="1" />
<file name="tools2.svg" server="ftp.mustersite.ch/httpdocs/homepage-maker/" local="131566905431701352" remote="131554039200000000" Dst="1" />
<file name="trash-bin.svg" server="ftp.mustersite.ch/httpdocs/homepage-maker/" local="131566905432809288" remote="131554039200000000" Dst="1" />
<file name="umbrella.svg" server="ftp.mustersite.ch/httpdocs/homepage-maker/" local="131566905433210348" remote="131554039200000000" Dst="1" />
<file name="user01.svg" server="ftp.mustersite.ch/httpdocs/homepage-maker/" local="131566905433255472" remote="131554039200000000" Dst="1" />
<file name="user02.svg" server="ftp.mustersite.ch/httpdocs/homepage-maker/" local="131566905434228067" remote="131554039200000000" Dst="1" />
<file name="user03.svg" server="ftp.mustersite.ch/httpdocs/homepage-maker/" local="131566905434689296" remote="131554039200000000" Dst="1" />
<file name="user04.svg" server="ftp.mustersite.ch/httpdocs/homepage-maker/" local="131566905434749446" remote="131554039200000000" Dst="1" />
<file name="user05.svg" server="ftp.mustersite.ch/httpdocs/homepage-maker/" local="131566905436318614" remote="131554039200000000" Dst="1" />
<file name="user06.svg" server="ftp.mustersite.ch/httpdocs/homepage-maker/" local="131566905436564267" remote="131554039200000000" Dst="1" />
<file name="user07.svg" server="ftp.mustersite.ch/httpdocs/homepage-maker/" local="131566905436845013" remote="131554039200000000" Dst="1" />
<file name="user09.svg" server="ftp.mustersite.ch/httpdocs/homepage-maker/" local="131566905437792837" remote="131554039200000000" Dst="1" />
<file name="users.svg" server="ftp.mustersite.ch/httpdocs/homepage-maker/" local="131566905437993653" remote="131554039200000000" Dst="1" />
<file name="user08.svg" server="ftp.mustersite.ch/httpdocs/homepage-maker/" local="131566905438178863" remote="131554039200000000" Dst="1" />
<file name="venn-diagram.svg" server="ftp.mustersite.ch/httpdocs/homepage-maker/" local="131566905439116628" remote="131554039200000000" Dst="1" />
<file name="wallet.svg" server="ftp.mustersite.ch/httpdocs/homepage-maker/" local="131566905439437220" remote="131554039200000000" Dst="1" />
<file name="wrench.svg" server="ftp.mustersite.ch/httpdocs/homepage-maker/" local="131566905439487350" remote="131554039200000000" Dst="1" />
<file name="yen.svg" server="ftp.mustersite.ch/httpdocs/homepage-maker/" local="131566905440399768" remote="131554039200000000" Dst="1" />
<file name="yinyang.svg" server="ftp.mustersite.ch/httpdocs/homepage-maker/" local="131566905440770753" remote="131554039200000000" Dst="1" />
<file name="NewTux.svg" server="ftp.mustersite.ch/httpdocs/clone/" local="131782816706153066" remote="131782032000000000" Dst="2" />
<file name="abacus.svg" server="ftp.mustersite.ch/httpdocs/clone/" local="131782816706621538" remote="131782031400000000" Dst="2" />
<file name="address-book.svg" server="ftp.mustersite.ch/httpdocs/clone/" local="131782816708653164" remote="131782031400000000" Dst="2" />
<file name="address-book2.svg" server="ftp.mustersite.ch/httpdocs/clone/" local="131782816709121628" remote="131782031400000000" Dst="2" />
<file name="aim.svg" server="ftp.mustersite.ch/httpdocs/clone/" local="131782816710996968" remote="131782031400000000" Dst="2" />
<file name="alarm.svg" server="ftp.mustersite.ch/httpdocs/clone/" local="131782816711465744" remote="131782031400000000" Dst="2" />
<file name="apple.svg" server="ftp.mustersite.ch/httpdocs/clone/" local="131782816713340841" remote="131782031400000000" Dst="2" />
<file name="arrow-left.svg" server="ftp.mustersite.ch/httpdocs/clone/" local="131782816713809484" remote="131782031400000000" Dst="2" />
<file name="arrow-right.svg" server="ftp.mustersite.ch/httpdocs/clone/" local="131782816715840994" remote="131782031400000000" Dst="2" />
<file name="arrows-updown.svg" server="ftp.mustersite.ch/httpdocs/clone/" local="131782816716309719" remote="131782031400000000" Dst="2" />
<file name="atm-cash.svg" server="ftp.mustersite.ch/httpdocs/clone/" local="131782816718966008" remote="131782031400000000" Dst="2" />
<file name="award1.svg" server="ftp.mustersite.ch/httpdocs/clone/" local="131782816719434784" remote="131782031400000000" Dst="2" />
<file name="award2.svg" server="ftp.mustersite.ch/httpdocs/clone/" local="131782816721466106" remote="131782031400000000" Dst="2" />
<file name="award3.svg" server="ftp.mustersite.ch/httpdocs/clone/" local="131782816721778601" remote="131782031400000000" Dst="2" />
<file name="award4.svg" server="ftp.mustersite.ch/httpdocs/clone/" local="131782816723809962" remote="131782031400000000" Dst="2" />
<file name="award5.svg" server="ftp.mustersite.ch/httpdocs/clone/" local="131782816725528624" remote="131782031400000000" Dst="2" />
<file name="badge01.svg" server="ftp.mustersite.ch/httpdocs/clone/" local="131782816725997271" remote="131782031400000000" Dst="2" />
<file name="badge02.svg" server="ftp.mustersite.ch/httpdocs/clone/" local="131782816727872629" remote="131782031400000000" Dst="2" />
<file name="bank.svg" server="ftp.mustersite.ch/httpdocs/clone/" local="131782816728341110" remote="131782031400000000" Dst="2" />
<file name="bank2.svg" server="ftp.mustersite.ch/httpdocs/clone/" local="131782816730216164" remote="131782031400000000" Dst="2" />
<file name="bell.svg" server="ftp.mustersite.ch/httpdocs/clone/" local="131782816730528940" remote="131782031400000000" Dst="2" />
<file name="binoculars.svg" server="ftp.mustersite.ch/httpdocs/clone/" local="131782816732559994" remote="131782031400000000" Dst="2" />
<file name="bomb.svg" server="ftp.mustersite.ch/httpdocs/clone/" local="131782816733029294" remote="131782031400000000" Dst="2" />
<file name="bonsai.svg" server="ftp.mustersite.ch/httpdocs/clone/" local="131782816735372599" remote="131782031400000000" Dst="2" />
<file name="book-apple.svg" server="ftp.mustersite.ch/httpdocs/clone/" local="131782816735685110" remote="131782031400000000" Dst="2" />
<file name="book.svg" server="ftp.mustersite.ch/httpdocs/clone/" local="131782816750841899" remote="131782031400000000" Dst="2" />
<file name="bookmark.svg" server="ftp.mustersite.ch/httpdocs/clone/" local="131782816751154415" remote="131782031400000000" Dst="2" />
<file name="box.svg" server="ftp.mustersite.ch/httpdocs/clone/" local="131782816753185908" remote="131782031400000000" Dst="2" />
<file name="brain.svg" server="ftp.mustersite.ch/httpdocs/clone/" local="131782816753654474" remote="131782031400000000" Dst="2" />
<file name="briefcase.svg" server="ftp.mustersite.ch/httpdocs/clone/" local="131782816755998321" remote="131782031400000000" Dst="2" />
<file name="browser01.svg" server="ftp.mustersite.ch/httpdocs/clone/" local="131782816758029926" remote="131782032000000000" Dst="2" />
<file name="browser02.svg" server="ftp.mustersite.ch/httpdocs/clone/" local="131782816758498701" remote="131782032000000000" Dst="2" />
<file name="buildings.svg" server="ftp.mustersite.ch/httpdocs/clone/" local="131782816760217261" remote="131782032000000000" Dst="2" />
<file name="buy-sign.svg" server="ftp.mustersite.ch/httpdocs/clone/" local="131782816760529802" remote="131782032000000000" Dst="2" />
<file name="calculator1.svg" server="ftp.mustersite.ch/httpdocs/clone/" local="131782816762561044" remote="131782032000000000" Dst="2" />
<file name="calculator2.svg" server="ftp.mustersite.ch/httpdocs/clone/" local="131782816762873555" remote="131782032000000000" Dst="2" />
<file name="calculator3.svg" server="ftp.mustersite.ch/httpdocs/clone/" local="131782816764748652" remote="131782032000000000" Dst="2" />
<file name="calendar1.svg" server="ftp.mustersite.ch/httpdocs/clone/" local="131782816765061428" remote="131782032000000000" Dst="2" />
<file name="calendar2.svg" server="ftp.mustersite.ch/httpdocs/clone/" local="131782816767092746" remote="131782032000000000" Dst="2" />
<file name="calendar3.svg" server="ftp.mustersite.ch/httpdocs/clone/" local="131782816767561475" remote="131782032000000000" Dst="2" />
<file name="calendar4.svg" server="ftp.mustersite.ch/httpdocs/clone/" local="131782816769436329" remote="131782032000000000" Dst="2" />
<file name="calendar5.svg" server="ftp.mustersite.ch/httpdocs/clone/" local="131782816769748831" remote="131782032000000000" Dst="2" />
<file name="certificate.svg" server="ftp.mustersite.ch/httpdocs/clone/" local="131782816771780504" remote="131782032000000000" Dst="2" />
<file name="champagne.svg" server="ftp.mustersite.ch/httpdocs/clone/" local="131782816772092930" remote="131782032000000000" Dst="2" />
<file name="character01.svg" server="ftp.mustersite.ch/httpdocs/clone/" local="131782816774749296" remote="131782032000000000" Dst="2" />
<file name="character02.svg" server="ftp.mustersite.ch/httpdocs/clone/" local="131782816776780338" remote="131782032000000000" Dst="2" />
<file name="character03.svg" server="ftp.mustersite.ch/httpdocs/clone/" local="131782816776936585" remote="131782032000000000" Dst="2" />
<file name="character04.svg" server="ftp.mustersite.ch/httpdocs/clone/" local="131782816778811895" remote="131782032000000000" Dst="2" />
<file name="character05.svg" server="ftp.mustersite.ch/httpdocs/clone/" local="131782816779280705" remote="131782032000000000" Dst="2" />
<file name="character06.svg" server="ftp.mustersite.ch/httpdocs/clone/" local="131782816781624227" remote="131782032000000000" Dst="2" />
<file name="character07.svg" server="ftp.mustersite.ch/httpdocs/clone/" local="131782816781937016" remote="131782032000000000" Dst="2" />
<file name="character08.svg" server="ftp.mustersite.ch/httpdocs/clone/" local="131782816784124859" remote="131782032000000000" Dst="2" />
<file name="chart-analysis.svg" server="ftp.mustersite.ch/httpdocs/clone/" local="131782816784593387" remote="131782032000000000" Dst="2" />
<file name="chart-board.svg" server="ftp.mustersite.ch/httpdocs/clone/" local="131782816786781042" remote="131782032000000000" Dst="2" />
<file name="chart-pyramid.svg" server="ftp.mustersite.ch/httpdocs/clone/" local="131782816787249702" remote="131782032000000000" Dst="2" />
<file name="chart01.svg" server="ftp.mustersite.ch/httpdocs/clone/" local="131782816789593579" remote="131782032000000000" Dst="2" />
<file name="chart02.svg" server="ftp.mustersite.ch/httpdocs/clone/" local="131782816790062307" remote="131782032000000000" Dst="2" />
<file name="chart03.svg" server="ftp.mustersite.ch/httpdocs/clone/" local="131782816791937097" remote="131782032000000000" Dst="2" />
<file name="chart04.svg" server="ftp.mustersite.ch/httpdocs/clone/" local="131782816792406141" remote="131782032000000000" Dst="2" />
<file name="chart05.svg" server="ftp.mustersite.ch/httpdocs/clone/" local="131782816794437472" remote="131782032000000000" Dst="2" />
<file name="chart06.svg" server="ftp.mustersite.ch/httpdocs/clone/" local="131782816796000109" remote="131782032000000000" Dst="2" />
<file name="chart07.svg" server="ftp.mustersite.ch/httpdocs/clone/" local="131782816796468829" remote="131782032000000000" Dst="2" />
<file name="chart08.svg" server="ftp.mustersite.ch/httpdocs/clone/" local="131782816798500114" remote="131782032000000000" Dst="2" />
<file name="chart09.svg" server="ftp.mustersite.ch/httpdocs/clone/" local="131782816799124978" remote="131782032000000000" Dst="2" />
<file name="chart10.svg" server="ftp.mustersite.ch/httpdocs/clone/" local="131782816801000191" remote="131782032000000000" Dst="2" />
<file name="chart11.svg" server="ftp.mustersite.ch/httpdocs/clone/" local="131782816801312740" remote="131782032000000000" Dst="2" />
<file name="chart12.svg" server="ftp.mustersite.ch/httpdocs/clone/" local="131782816803656809" remote="131782032000000000" Dst="2" />
<file name="chart13.svg" server="ftp.mustersite.ch/httpdocs/clone/" local="131782816804125034" remote="131782032000000000" Dst="2" />
<file name="chart14.svg" server="ftp.mustersite.ch/httpdocs/clone/" local="131782816806156672" remote="131782032000000000" Dst="2" />
<file name="chart15.svg" server="ftp.mustersite.ch/httpdocs/clone/" local="131782816806469132" remote="131782032000000000" Dst="2" />
<file name="chart16.svg" server="ftp.mustersite.ch/httpdocs/clone/" local="131782816808344217" remote="131782032000000000" Dst="2" />
<file name="chart17.svg" server="ftp.mustersite.ch/httpdocs/clone/" local="131782816808812975" remote="131782032000000000" Dst="2" />
<file name="chart18.svg" server="ftp.mustersite.ch/httpdocs/clone/" local="131782816810844404" remote="131782032000000000" Dst="2" />
<file name="chart19.svg" server="ftp.mustersite.ch/httpdocs/clone/" local="131782816811157078" remote="131782032000000000" Dst="2" />
<file name="chart20.svg" server="ftp.mustersite.ch/httpdocs/clone/" local="131782816813188162" remote="131782032000000000" Dst="2" />
<file name="chart21.svg" server="ftp.mustersite.ch/httpdocs/clone/" local="131782816815063037" remote="131782032000000000" Dst="2" />
<file name="chat.svg" server="ftp.mustersite.ch/httpdocs/clone/" local="131782816815375761" remote="131782032000000000" Dst="2" />
<file name="checklist.svg" server="ftp.mustersite.ch/httpdocs/clone/" local="131782816817407046" remote="131782032000000000" Dst="2" />
<file name="checklist2.svg" server="ftp.mustersite.ch/httpdocs/clone/" local="131782816817875813" remote="131782032000000000" Dst="2" />
<file name="checklist3.svg" server="ftp.mustersite.ch/httpdocs/clone/" local="131782816819750594" remote="131782032000000000" Dst="2" />
<file name="chemistry.svg" server="ftp.mustersite.ch/httpdocs/clone/" local="131782816820219651" remote="131782032000000000" Dst="2" />
<file name="chess-knight.svg" server="ftp.mustersite.ch/httpdocs/clone/" local="131782816822094731" remote="131782032000000000" Dst="2" />
<file name="chess-rook.svg" server="ftp.mustersite.ch/httpdocs/clone/" local="131782816822563481" remote="131782032000000000" Dst="2" />
<file name="chess.svg" server="ftp.mustersite.ch/httpdocs/clone/" local="131782816824438586" remote="131782032000000000" Dst="2" />
<file name="clock.svg" server="ftp.mustersite.ch/httpdocs/clone/" local="131782816824907067" remote="131782032000000000" Dst="2" />
<file name="closed-sign.svg" server="ftp.mustersite.ch/httpdocs/clone/" local="131782816826782134" remote="131782032000000000" Dst="2" />
<file name="cloud-coins.svg" server="ftp.mustersite.ch/httpdocs/clone/" local="131782816827250893" remote="131782032000000000" Dst="2" />
<file name="cloud-down.svg" server="ftp.mustersite.ch/httpdocs/clone/" local="131782816829126442" remote="131782032000000000" Dst="2" />
<file name="cloud-up.svg" server="ftp.mustersite.ch/httpdocs/clone/" local="131782816829594961" remote="131782032000000000" Dst="2" />
<file name="coffee.svg" server="ftp.mustersite.ch/httpdocs/clone/" local="131782816831470033" remote="131782032000000000" Dst="2" />
<file name="conference.svg" server="ftp.mustersite.ch/httpdocs/clone/" local="131782816833188844" remote="131782032000000000" Dst="2" />
<file name="contact-book.svg" server="ftp.mustersite.ch/httpdocs/clone/" local="131782816833657876" remote="131782032000000000" Dst="2" />
<file name="coupon.svg" server="ftp.mustersite.ch/httpdocs/clone/" local="131782816835532687" remote="131782032000000000" Dst="2" />
<file name="credit-card.svg" server="ftp.mustersite.ch/httpdocs/clone/" local="131782816836001206" remote="131782032000000000" Dst="2" />
<file name="crown.svg" server="ftp.mustersite.ch/httpdocs/clone/" local="131782816838032644" remote="131782032000000000" Dst="2" />
<file name="currencies.svg" server="ftp.mustersite.ch/httpdocs/clone/" local="131782816838345305" remote="131782032000000000" Dst="2" />
<file name="database.svg" server="ftp.mustersite.ch/httpdocs/clone/" local="131782816840376636" remote="131782032000000000" Dst="2" />
<file name="delivery.svg" server="ftp.mustersite.ch/httpdocs/clone/" local="131782816840689113" remote="131782032000000000" Dst="2" />
<file name="diagram-hierarchy.svg" server="ftp.mustersite.ch/httpdocs/clone/" local="131782816842564223" remote="131782032000000000" Dst="2" />
<file name="diamond.svg" server="ftp.mustersite.ch/httpdocs/clone/" local="131782816843032960" remote="131782032000000000" Dst="2" />
<file name="dollar.svg" server="ftp.mustersite.ch/httpdocs/clone/" local="131782816844908036" remote="131782032000000000" Dst="2" />
<file name="drawer.svg" server="ftp.mustersite.ch/httpdocs/clone/" local="131782816845376513" remote="131782032000000000" Dst="2" />
<file name="egg.svg" server="ftp.mustersite.ch/httpdocs/clone/" local="131782816847251610" remote="131782032000000000" Dst="2" />
<file name="emblem.svg" server="ftp.mustersite.ch/httpdocs/clone/" local="131782816847720641" remote="131782032000000000" Dst="2" />
<file name="envelope-money.svg" server="ftp.mustersite.ch/httpdocs/clone/" local="131782816849595717" remote="131782032000000000" Dst="2" />
<file name="envelopes.svg" server="ftp.mustersite.ch/httpdocs/clone/" local="131782816851470844" remote="131782032000000000" Dst="2" />
<file name="euro.svg" server="ftp.mustersite.ch/httpdocs/clone/" local="131782816851782996" remote="131782032000000000" Dst="2" />
<file name="exchange.svg" server="ftp.mustersite.ch/httpdocs/clone/" local="131782816853658358" remote="131782032000000000" Dst="2" />
<file name="exit.svg" server="ftp.mustersite.ch/httpdocs/clone/" local="131782816854127121" remote="131782032000000000" Dst="2" />
<file name="factory.svg" server="ftp.mustersite.ch/httpdocs/clone/" local="131782816856158452" remote="131782032000000000" Dst="2" />
<file name="fax.svg" server="ftp.mustersite.ch/httpdocs/clone/" local="131782816856470690" remote="131782032000000000" Dst="2" />
<file name="file01.svg" server="ftp.mustersite.ch/httpdocs/clone/" local="131782816858346048" remote="131782032000000000" Dst="2" />
<file name="file02.svg" server="ftp.mustersite.ch/httpdocs/clone/" local="131782816858658563" remote="131782032000000000" Dst="2" />
<file name="file03.svg" server="ftp.mustersite.ch/httpdocs/clone/" local="131782816860533605" remote="131782032000000000" Dst="2" />
<file name="file04.svg" server="ftp.mustersite.ch/httpdocs/clone/" local="131782816861002111" remote="131782032000000000" Dst="2" />
<file name="file05.svg" server="ftp.mustersite.ch/httpdocs/clone/" local="131782816862720910" remote="131782032000000000" Dst="2" />
<file name="file06.svg" server="ftp.mustersite.ch/httpdocs/clone/" local="131782816863189937" remote="131782032000000000" Dst="2" />
<file name="file07.svg" server="ftp.mustersite.ch/httpdocs/clone/" local="131782816865065043" remote="131782032000000000" Dst="2" />
<file name="file08.svg" server="ftp.mustersite.ch/httpdocs/clone/" local="131782816865533515" remote="131782032000000000" Dst="2" />
<file name="file09.svg" server="ftp.mustersite.ch/httpdocs/clone/" local="131782816867408928" remote="131782032000000000" Dst="2" />
<file name="file10.svg" server="ftp.mustersite.ch/httpdocs/clone/" local="131782816869127646" remote="131782032000000000" Dst="2" />
<file name="files.svg" server="ftp.mustersite.ch/httpdocs/clone/" local="131782816869439875" remote="131782032000000000" Dst="2" />
<file name="fire.svg" server="ftp.mustersite.ch/httpdocs/clone/" local="131782816871471471" remote="131782032000000000" Dst="2" />
<file name="fish.svg" server="ftp.mustersite.ch/httpdocs/clone/" local="131782816871784025" remote="131782032000000000" Dst="2" />
<file name="flag.svg" server="ftp.mustersite.ch/httpdocs/clone/" local="131782816873971603" remote="131782032000000000" Dst="2" />
<file name="folder-add.svg" server="ftp.mustersite.ch/httpdocs/clone/" local="131782816874127910" remote="131782032000000000" Dst="2" />
<file name="folder-delete.svg" server="ftp.mustersite.ch/httpdocs/clone/" local="131782816876315702" remote="131782032000000000" Dst="2" />
<file name="folder-online.svg" server="ftp.mustersite.ch/httpdocs/clone/" local="131782816876627953" remote="131782032000000000" Dst="2" />
<file name="folder-private.svg" server="ftp.mustersite.ch/httpdocs/clone/" local="131782816878815561" remote="131782032000000000" Dst="2" />
<file name="folder-remove.svg" server="ftp.mustersite.ch/httpdocs/clone/" local="131782816879284243" remote="131782032000000000" Dst="2" />
<file name="folder.svg" server="ftp.mustersite.ch/httpdocs/clone/" local="131782816881159370" remote="131782032000000000" Dst="2" />
<file name="folders.svg" server="ftp.mustersite.ch/httpdocs/clone/" local="131782816881784068" remote="131782032000000000" Dst="2" />
<file name="funnel-money.svg" server="ftp.mustersite.ch/httpdocs/clone/" local="131782816883971650" remote="131782032000000000" Dst="2" />
<file name="funnel.svg" server="ftp.mustersite.ch/httpdocs/clone/" local="131782816884284473" remote="131782032000000000" Dst="2" />
<file name="gauge.svg" server="ftp.mustersite.ch/httpdocs/clone/" local="131782816886315860" remote="131782032000000000" Dst="2" />
<file name="gauge2.svg" server="ftp.mustersite.ch/httpdocs/clone/" local="131782816888190547" remote="131782032000000000" Dst="2" />
<file name="gears1.svg" server="ftp.mustersite.ch/httpdocs/clone/" local="131782816888659604" remote="131782032000000000" Dst="2" />
<file name="gears2.svg" server="ftp.mustersite.ch/httpdocs/clone/" local="131782816890534484" remote="131782032000000000" Dst="2" />
<file name="glasses-moustache.svg" server="ftp.mustersite.ch/httpdocs/clone/" local="131782816891003430" remote="131782032000000000" Dst="2" />
<file name="globe-money.svg" server="ftp.mustersite.ch/httpdocs/clone/" local="131782816893034783" remote="131782032000000000" Dst="2" />
<file name="globe.svg" server="ftp.mustersite.ch/httpdocs/clone/" local="131782816893347255" remote="131782032000000000" Dst="2" />
<file name="globe2.svg" server="ftp.mustersite.ch/httpdocs/clone/" local="131782816895222207" remote="131782032000000000" Dst="2" />
<file name="graduation-hat.svg" server="ftp.mustersite.ch/httpdocs/clone/" local="131782816895691106" remote="131782032000000000" Dst="2" />
<file name="hand-globe.svg" server="ftp.mustersite.ch/httpdocs/clone/" local="131782816897409662" remote="131782032000000000" Dst="2" />
<file name="hand-key.svg" server="ftp.mustersite.ch/httpdocs/clone/" local="131782816897878698" remote="131782032000000000" Dst="2" />
<file name="hand-money.svg" server="ftp.mustersite.ch/httpdocs/clone/" local="131782816899753462" remote="131782032000000000" Dst="2" />
<file name="hand-money2.svg" server="ftp.mustersite.ch/httpdocs/clone/" local="131782816900222549" remote="131782032000000000" Dst="2" />
<file name="handshake.svg" server="ftp.mustersite.ch/httpdocs/clone/" local="131782816902097590" remote="131782032000000000" Dst="2" />
<file name="hat-moustache.svg" server="ftp.mustersite.ch/httpdocs/clone/" local="131782816902410358" remote="131782032000000000" Dst="2" />
<file name="hat.svg" server="ftp.mustersite.ch/httpdocs/clone/" local="131782816904285186" remote="131782032000000000" Dst="2" />
<file name="head-arrows.svg" server="ftp.mustersite.ch/httpdocs/clone/" local="131782816906160245" remote="131782032000000000" Dst="2" />
<file name="head-battery.svg" server="ftp.mustersite.ch/httpdocs/clone/" local="131782816906629028" remote="131782032000000000" Dst="2" />
<file name="head-check.svg" server="ftp.mustersite.ch/httpdocs/clone/" local="131782816908504057" remote="131782032000000000" Dst="2" />
<file name="head-compass.svg" server="ftp.mustersite.ch/httpdocs/clone/" local="131782816908816462" remote="131782032000000000" Dst="2" />
<file name="head-dollar.svg" server="ftp.mustersite.ch/httpdocs/clone/" local="131782816910847883" remote="131782032000000000" Dst="2" />
<file name="head-exclamation.svg" server="ftp.mustersite.ch/httpdocs/clone/" local="131782816911160407" remote="131782032000000000" Dst="2" />
<file name="head-flash.svg" server="ftp.mustersite.ch/httpdocs/clone/" local="131782816913191712" remote="131782032000000000" Dst="2" />
<file name="head-gauge.svg" server="ftp.mustersite.ch/httpdocs/clone/" local="131782816913504254" remote="131782032000000000" Dst="2" />
<file name="head-gears.svg" server="ftp.mustersite.ch/httpdocs/clone/" local="131782816915535278" remote="131782032000000000" Dst="2" />
<file name="head-hourglass.svg" server="ftp.mustersite.ch/httpdocs/clone/" local="131782816915848113" remote="131782032000000000" Dst="2" />
<file name="head-idea.svg" server="ftp.mustersite.ch/httpdocs/clone/" local="131782816917722856" remote="131782032000000000" Dst="2" />
<file name="head-question.svg" server="ftp.mustersite.ch/httpdocs/clone/" local="131782816918191623" remote="131782032000000000" Dst="2" />
<file name="head-structure.svg" server="ftp.mustersite.ch/httpdocs/clone/" local="131782816920222950" remote="131782032000000000" Dst="2" />
<file name="head.svg" server="ftp.mustersite.ch/httpdocs/clone/" local="131782816920535743" remote="131782032000000000" Dst="2" />
<file name="headquarters.svg" server="ftp.mustersite.ch/httpdocs/clone/" local="131782816922410806" remote="131782032000000000" Dst="2" />
<file name="hourglass.svg" server="ftp.mustersite.ch/httpdocs/clone/" local="131782816924129634" remote="131782032000000000" Dst="2" />
<file name="hours.svg" server="ftp.mustersite.ch/httpdocs/clone/" local="131782816924598418" remote="131782032000000000" Dst="2" />
<file name="incoming.svg" server="ftp.mustersite.ch/httpdocs/clone/" local="131782816926473460" remote="131782032000000000" Dst="2" />
<file name="ingots.svg" server="ftp.mustersite.ch/httpdocs/clone/" local="131782816926941966" remote="131782032000000000" Dst="2" />
<file name="key.svg" server="ftp.mustersite.ch/httpdocs/clone/" local="131782816928817328" remote="131782032000000000" Dst="2" />
<file name="key2.svg" server="ftp.mustersite.ch/httpdocs/clone/" local="131782816929286313" remote="131782032000000000" Dst="2" />
<file name="keyboard.svg" server="ftp.mustersite.ch/httpdocs/clone/" local="131782816931317520" remote="131782032000000000" Dst="2" />
<file name="label.svg" server="ftp.mustersite.ch/httpdocs/clone/" local="131782816931629920" remote="131782032000000000" Dst="2" />
<file name="lamp.svg" server="ftp.mustersite.ch/httpdocs/clone/" local="131782816933661235" remote="131782032000000000" Dst="2" />
<file name="laptop-article.svg" server="ftp.mustersite.ch/httpdocs/clone/" local="131782816933973439" remote="131782032000000000" Dst="2" />
<file name="laptop-cart.svg" server="ftp.mustersite.ch/httpdocs/clone/" local="131782816936005018" remote="131782032000000000" Dst="2" />
<file name="laptop-chart.svg" server="ftp.mustersite.ch/httpdocs/clone/" local="131782816936317563" remote="131782032000000000" Dst="2" />
<file name="laptop-chart2.svg" server="ftp.mustersite.ch/httpdocs/clone/" local="131782816938192344" remote="131782032000000000" Dst="2" />
<file name="laptop-diagram.svg" server="ftp.mustersite.ch/httpdocs/clone/" local="131782816938661423" remote="131782032000000000" Dst="2" />
<file name="laptop-envelope.svg" server="ftp.mustersite.ch/httpdocs/clone/" local="131782816940536451" remote="131782032000000000" Dst="2" />
<file name="laptop-finance.svg" server="ftp.mustersite.ch/httpdocs/clone/" local="131782816942255139" remote="131782032000000000" Dst="2" />
<file name="laptop-privacy.svg" server="ftp.mustersite.ch/httpdocs/clone/" local="131782816942723752" remote="131782032000000000" Dst="2" />
<file name="laptop-settings.svg" server="ftp.mustersite.ch/httpdocs/clone/" local="131782816947880460" remote="131782032000000000" Dst="2" />
<file name="laptop-user.svg" server="ftp.mustersite.ch/httpdocs/clone/" local="131782816948505487" remote="131782032000000000" Dst="2" />
<file name="laptop.svg" server="ftp.mustersite.ch/httpdocs/clone/" local="131782816950536857" remote="131782032000000000" Dst="2" />
<file name="lightbulb-green.svg" server="ftp.mustersite.ch/httpdocs/clone/" local="131782816951005867" remote="131782032000000000" Dst="2" />
<file name="lightbulb.svg" server="ftp.mustersite.ch/httpdocs/clone/" local="131782816952880763" remote="131782032000000000" Dst="2" />
<file name="lightning.svg" server="ftp.mustersite.ch/httpdocs/clone/" local="131782816953349133" remote="131782032000000000" Dst="2" />
<file name="like.svg" server="ftp.mustersite.ch/httpdocs/clone/" local="131782816955224328" remote="131782032000000000" Dst="2" />
<file name="lock.svg" server="ftp.mustersite.ch/httpdocs/clone/" local="131782816955537079" remote="131782032000000000" Dst="2" />
<file name="magnet-money.svg" server="ftp.mustersite.ch/httpdocs/clone/" local="131782816957568367" remote="131782032000000000" Dst="2" />
<file name="magnifying-glass.svg" server="ftp.mustersite.ch/httpdocs/clone/" local="131782816957880938" remote="131782032000000000" Dst="2" />
<file name="manager-globe.svg" server="ftp.mustersite.ch/httpdocs/clone/" local="131782816959912163" remote="131782032000000000" Dst="2" />
<file name="manager-idea.svg" server="ftp.mustersite.ch/httpdocs/clone/" local="131782816960380635" remote="131782032000000000" Dst="2" />
<file name="manager01.svg" server="ftp.mustersite.ch/httpdocs/clone/" local="131782816962256078" remote="131782032000000000" Dst="2" />
<file name="manager02.svg" server="ftp.mustersite.ch/httpdocs/clone/" local="131782816964131060" remote="131782032000000000" Dst="2" />
<file name="meditation.svg" server="ftp.mustersite.ch/httpdocs/clone/" local="131782816964287341" remote="131782032000000000" Dst="2" />
<file name="megaphone.svg" server="ftp.mustersite.ch/httpdocs/clone/" local="131782816966162468" remote="131782032000000000" Dst="2" />
<file name="money-growth.svg" server="ftp.mustersite.ch/httpdocs/clone/" local="131782816966787414" remote="131782032000000000" Dst="2" />
<file name="money-scales.svg" server="ftp.mustersite.ch/httpdocs/clone/" local="131782816968974996" remote="131782032000000000" Dst="2" />
<file name="money.svg" server="ftp.mustersite.ch/httpdocs/clone/" local="131782816969287213" remote="131782032000000000" Dst="2" />
<file name="money2.svg" server="ftp.mustersite.ch/httpdocs/clone/" local="131782816971318557" remote="131782032000000000" Dst="2" />
<file name="money3.svg" server="ftp.mustersite.ch/httpdocs/clone/" local="131782816971475077" remote="131782032000000000" Dst="2" />
<file name="money4.svg" server="ftp.mustersite.ch/httpdocs/clone/" local="131782816973506375" remote="131782032000000000" Dst="2" />
<file name="money5.svg" server="ftp.mustersite.ch/httpdocs/clone/" local="131782816973818647" remote="131782032000000000" Dst="2" />
<file name="money6.svg" server="ftp.mustersite.ch/httpdocs/clone/" local="131782816975850251" remote="131782032000000000" Dst="2" />
<file name="monitor.svg" server="ftp.mustersite.ch/httpdocs/clone/" local="131782816976162746" remote="131782032000000000" Dst="2" />
<file name="mouse.svg" server="ftp.mustersite.ch/httpdocs/clone/" local="131782816978037518" remote="131782032000000000" Dst="2" />
<file name="nest-money.svg" server="ftp.mustersite.ch/httpdocs/clone/" local="131782816978506592" remote="131782032000000000" Dst="2" />
<file name="newspaper-jobs.svg" server="ftp.mustersite.ch/httpdocs/clone/" local="131782816980694132" remote="131782032000000000" Dst="2" />
<file name="newspaper-pen.svg" server="ftp.mustersite.ch/httpdocs/clone/" local="131782816982256752" remote="131782032000000000" Dst="2" />
<file name="newspaper.svg" server="ftp.mustersite.ch/httpdocs/clone/" local="131782816982569229" remote="131782032000000000" Dst="2" />
<file name="note-paper.svg" server="ftp.mustersite.ch/httpdocs/clone/" local="131782816984444284" remote="131782032000000000" Dst="2" />
<file name="office-chair.svg" server="ftp.mustersite.ch/httpdocs/clone/" local="131782816985225558" remote="131782032000000000" Dst="2" />
<file name="open-sign.svg" server="ftp.mustersite.ch/httpdocs/clone/" local="131782816987413123" remote="131782032000000000" Dst="2" />
<file name="outgoing.svg" server="ftp.mustersite.ch/httpdocs/clone/" local="131782816987881903" remote="131782032000000000" Dst="2" />
<file name="paper-clip.svg" server="ftp.mustersite.ch/httpdocs/clone/" local="131782816989756991" remote="131782032000000000" Dst="2" />
<file name="paper-plane.svg" server="ftp.mustersite.ch/httpdocs/clone/" local="131782816990069498" remote="131782032000000000" Dst="2" />
<file name="pen.svg" server="ftp.mustersite.ch/httpdocs/clone/" local="131782816992100872" remote="131782032000000000" Dst="2" />
<file name="pen2.svg" server="ftp.mustersite.ch/httpdocs/clone/" local="131782816992413597" remote="131782032000000000" Dst="2" />
<file name="pencil.svg" server="ftp.mustersite.ch/httpdocs/clone/" local="131782816994444664" remote="131782032000000000" Dst="2" />
<file name="pens-pencils.svg" server="ftp.mustersite.ch/httpdocs/clone/" local="131782816994757192" remote="131782032000000000" Dst="2" />
<file name="people-arrows06.svg" server="ftp.mustersite.ch/httpdocs/clone/" local="131782816996944561" remote="131782032000000000" Dst="2" />
<file name="people-gears.svg" server="ftp.mustersite.ch/httpdocs/clone/" local="131782816997257260" remote="131782032000000000" Dst="2" />
<file name="people-handshake.svg" server="ftp.mustersite.ch/httpdocs/clone/" local="131782816999445120" remote="131782032000000000" Dst="2" />
<file name="people-idea.svg" server="ftp.mustersite.ch/httpdocs/clone/" local="131782817001163710" remote="131782032000000000" Dst="2" />
<file name="people-meeting.svg" server="ftp.mustersite.ch/httpdocs/clone/" local="131782817001476119" remote="131782032000000000" Dst="2" />
<file name="people-meeting02.svg" server="ftp.mustersite.ch/httpdocs/clone/" local="131782817003663783" remote="131782032000000000" Dst="2" />
<file name="people-search01.svg" server="ftp.mustersite.ch/httpdocs/clone/" local="131782817004132498" remote="131782032000000000" Dst="2" />
<file name="people-search02.svg" server="ftp.mustersite.ch/httpdocs/clone/" local="131782817006319782" remote="131782032000000000" Dst="2" />
<file name="people-structure.svg" server="ftp.mustersite.ch/httpdocs/clone/" local="131782817006632579" remote="131782032000000000" Dst="2" />
<file name="people-structure01.svg" server="ftp.mustersite.ch/httpdocs/clone/" local="131782817008663894" remote="131782032000000000" Dst="2" />
<file name="people-structure02.svg" server="ftp.mustersite.ch/httpdocs/clone/" local="131782817008976132" remote="131782032000000000" Dst="2" />
<file name="people-structure03.svg" server="ftp.mustersite.ch/httpdocs/clone/" local="131782817011007681" remote="131782032000000000" Dst="2" />
<file name="people-structure04.svg" server="ftp.mustersite.ch/httpdocs/clone/" local="131782817011164022" remote="131782032000000000" Dst="2" />
<file name="people-structure05.svg" server="ftp.mustersite.ch/httpdocs/clone/" local="131782817013039059" remote="131782032000000000" Dst="2" />
<file name="people-structure06.svg" server="ftp.mustersite.ch/httpdocs/clone/" local="131782817013507830" remote="131782032000000000" Dst="2" />
<file name="people-structure07.svg" server="ftp.mustersite.ch/httpdocs/clone/" local="131782817015382902" remote="131782032000000000" Dst="2" />
<file name="percent.svg" server="ftp.mustersite.ch/httpdocs/clone/" local="131782817015851664" remote="131782032000000000" Dst="2" />
<file name="periscopemoney.svg" server="ftp.mustersite.ch/httpdocs/clone/" local="131782817017726821" remote="131782032000000000" Dst="2" />
<file name="person-arrows01.svg" server="ftp.mustersite.ch/httpdocs/clone/" local="131782817019445530" remote="131782032000000000" Dst="2" />
<file name="person-arrows012.svg" server="ftp.mustersite.ch/httpdocs/clone/" local="131782817019914297" remote="131782032000000000" Dst="2" />
<file name="person-arrows02.svg" server="ftp.mustersite.ch/httpdocs/clone/" local="131782817021945658" remote="131782032000000000" Dst="2" />
<file name="person-arrows022.svg" server="ftp.mustersite.ch/httpdocs/clone/" local="131782817022258148" remote="131782032000000000" Dst="2" />
<file name="person-arrows03.svg" server="ftp.mustersite.ch/httpdocs/clone/" local="131782817024133224" remote="131782032000000000" Dst="2" />
<file name="person-checkmark.svg" server="ftp.mustersite.ch/httpdocs/clone/" local="131782817024601978" remote="131782032000000000" Dst="2" />
<file name="person-cross.svg" server="ftp.mustersite.ch/httpdocs/clone/" local="131782817026633326" remote="131782032000000000" Dst="2" />
<file name="person-data.svg" server="ftp.mustersite.ch/httpdocs/clone/" local="131782817027102106" remote="131782032000000000" Dst="2" />
<file name="person-dollar.svg" server="ftp.mustersite.ch/httpdocs/clone/" local="131782817029133531" remote="131782032000000000" Dst="2" />
<file name="person-finance.svg" server="ftp.mustersite.ch/httpdocs/clone/" local="131782817029601991" remote="131782032000000000" Dst="2" />
<file name="person-flag.svg" server="ftp.mustersite.ch/httpdocs/clone/" local="131782817031477224" remote="131782032000000000" Dst="2" />
<file name="person-globe.svg" server="ftp.mustersite.ch/httpdocs/clone/" local="131782817031789718" remote="131782032000000000" Dst="2" />
<file name="person-idea02.svg" server="ftp.mustersite.ch/httpdocs/clone/" local="131782817033820913" remote="131782032000000000" Dst="2" />
<file name="person-info.svg" server="ftp.mustersite.ch/httpdocs/clone/" local="131782817034289817" remote="131782032000000000" Dst="2" />
<file name="person-puzzle.svg" server="ftp.mustersite.ch/httpdocs/clone/" local="131782817036321131" remote="131782032000000000" Dst="2" />
<file name="person-scales.svg" server="ftp.mustersite.ch/httpdocs/clone/" local="131782817037883520" remote="131782032000000000" Dst="2" />
<file name="person-time.svg" server="ftp.mustersite.ch/httpdocs/clone/" local="131782817038196155" remote="131782032000000000" Dst="2" />
<file name="person-umbrella.svg" server="ftp.mustersite.ch/httpdocs/clone/" local="131782817040071299" remote="131782032000000000" Dst="2" />
<file name="phone.svg" server="ftp.mustersite.ch/httpdocs/clone/" local="131782817040540049" remote="131782032000000000" Dst="2" />
<file name="pie-chart01.svg" server="ftp.mustersite.ch/httpdocs/clone/" local="131782817042883892" remote="131782032000000000" Dst="2" />
<file name="pie-chart02.svg" server="ftp.mustersite.ch/httpdocs/clone/" local="131782817043352650" remote="131782032000000000" Dst="2" />
<file name="piggy-bank.svg" server="ftp.mustersite.ch/httpdocs/clone/" local="131782817045540254" remote="131782032000000000" Dst="2" />
<file name="pin.svg" server="ftp.mustersite.ch/httpdocs/clone/" local="131782817046165229" remote="131782032000000000" Dst="2" />
<file name="plant-money.svg" server="ftp.mustersite.ch/httpdocs/clone/" local="131782817048352880" remote="131782032000000000" Dst="2" />
<file name="plant.svg" server="ftp.mustersite.ch/httpdocs/clone/" local="131782817048665050" remote="131782032000000000" Dst="2" />
<file name="pound.svg" server="ftp.mustersite.ch/httpdocs/clone/" local="131782817050540391" remote="131782032000000000" Dst="2" />
<file name="presentation.svg" server="ftp.mustersite.ch/httpdocs/clone/" local="131782817051009196" remote="131782032000000000" Dst="2" />
<file name="presentation02.svg" server="ftp.mustersite.ch/httpdocs/clone/" local="131782817052884528" remote="131782032000000000" Dst="2" />
<file name="preson-chart02.svg" server="ftp.mustersite.ch/httpdocs/clone/" local="131782817053196761" remote="131782032000000000" Dst="2" />
<file name="preson-chart03.svg" server="ftp.mustersite.ch/httpdocs/clone/" local="131782817055228106" remote="131782032000000000" Dst="2" />
<file name="preson-chart04.svg" server="ftp.mustersite.ch/httpdocs/clone/" local="131782817056946892" remote="131782032000000000" Dst="2" />
<file name="preson-laurels.svg" server="ftp.mustersite.ch/httpdocs/clone/" local="131782817057415641" remote="131782032000000000" Dst="2" />
<file name="preson-megaphone.svg" server="ftp.mustersite.ch/httpdocs/clone/" local="131782817059290730" remote="131782032000000000" Dst="2" />
<file name="preson-stairs.svg" server="ftp.mustersite.ch/httpdocs/clone/" local="131782817059603228" remote="131782032000000000" Dst="2" />
<file name="printer.svg" server="ftp.mustersite.ch/httpdocs/clone/" local="131782817061790824" remote="131782032000000000" Dst="2" />
<file name="profile.svg" server="ftp.mustersite.ch/httpdocs/clone/" local="131782817062103595" remote="131782032000000000" Dst="2" />
<file name="pulse.svg" server="ftp.mustersite.ch/httpdocs/clone/" local="131782817064290717" remote="131782032000000000" Dst="2" />
<file name="puzzle.svg" server="ftp.mustersite.ch/httpdocs/clone/" local="131782817064759416" remote="131782032000000000" Dst="2" />
<file name="quill.svg" server="ftp.mustersite.ch/httpdocs/clone/" local="131782817066634760" remote="131782032000000000" Dst="2" />
<file name="recycle.svg" server="ftp.mustersite.ch/httpdocs/clone/" local="131782817066947263" remote="131782032000000000" Dst="2" />
<file name="rocket.svg" server="ftp.mustersite.ch/httpdocs/clone/" local="131782817068978569" remote="131782032000000000" Dst="2" />
<file name="rocket2.svg" server="ftp.mustersite.ch/httpdocs/clone/" local="131782817069447327" remote="131782032000000000" Dst="2" />
<file name="ruble.svg" server="ftp.mustersite.ch/httpdocs/clone/" local="131782817071322407" remote="131782032000000000" Dst="2" />
<file name="ruler-compasses.svg" server="ftp.mustersite.ch/httpdocs/clone/" local="131782817071791191" remote="131782032000000000" Dst="2" />
<file name="safe.svg" server="ftp.mustersite.ch/httpdocs/clone/" local="131782817073666249" remote="131782032000000000" Dst="2" />
<file name="sale-sign.svg" server="ftp.mustersite.ch/httpdocs/clone/" local="131782817075385040" remote="131782032000000000" Dst="2" />
<file name="satellite-dish.svg" server="ftp.mustersite.ch/httpdocs/clone/" local="131782817075697423" remote="131782032000000000" Dst="2" />
<file name="scales.svg" server="ftp.mustersite.ch/httpdocs/clone/" local="131782817077572336" remote="131782032000000000" Dst="2" />
<file name="scissors.svg" server="ftp.mustersite.ch/httpdocs/clone/" local="131782817078041125" remote="131782032000000000" Dst="2" />
<file name="security.svg" server="ftp.mustersite.ch/httpdocs/clone/" local="131782817079916175" remote="131782032000000000" Dst="2" />
<file name="send.svg" server="ftp.mustersite.ch/httpdocs/clone/" local="131782817080228989" remote="131782032000000000" Dst="2" />
<file name="shield.svg" server="ftp.mustersite.ch/httpdocs/clone/" local="131782817082104056" remote="131782032000000000" Dst="2" />
<file name="shopping-cart.svg" server="ftp.mustersite.ch/httpdocs/clone/" local="131782817082573092" remote="131782032000000000" Dst="2" />
<file name="sign.svg" server="ftp.mustersite.ch/httpdocs/clone/" local="131782817084447890" remote="131782032000000000" Dst="2" />
<file name="smartphone-chart.svg" server="ftp.mustersite.ch/httpdocs/clone/" local="131782817084916627" remote="131782032000000000" Dst="2" />
<file name="smartphone-exclamation.svg" server="ftp.mustersite.ch/httpdocs/clone/" local="131782817086791694" remote="131782032000000000" Dst="2" />
<file name="smartphone-gears.svg" server="ftp.mustersite.ch/httpdocs/clone/" local="131782817087260184" remote="131782032000000000" Dst="2" />
<file name="smartphone-growth.svg" server="ftp.mustersite.ch/httpdocs/clone/" local="131782817089291886" remote="131782032000000000" Dst="2" />
<file name="smartphone-money.svg" server="ftp.mustersite.ch/httpdocs/clone/" local="131782817089604325" remote="131782032000000000" Dst="2" />
<file name="smartphone-user.svg" server="ftp.mustersite.ch/httpdocs/clone/" local="131782817091479401" remote="131782032000000000" Dst="2" />
<file name="smartphone.svg" server="ftp.mustersite.ch/httpdocs/clone/" local="131782817093198204" remote="131782032000000000" Dst="2" />
<file name="speaker.svg" server="ftp.mustersite.ch/httpdocs/clone/" local="131782817093510685" remote="131782032000000000" Dst="2" />
<file name="speaker02.svg" server="ftp.mustersite.ch/httpdocs/clone/" local="131782817095542000" remote="131782032000000000" Dst="2" />
<file name="speech-bubble.svg" server="ftp.mustersite.ch/httpdocs/clone/" local="131782817095854596" remote="131782032000000000" Dst="2" />
<file name="stamp.svg" server="ftp.mustersite.ch/httpdocs/clone/" local="131782817098198362" remote="131782032000000000" Dst="2" />
<file name="star.svg" server="ftp.mustersite.ch/httpdocs/clone/" local="131782817098510711" remote="131782032000000000" Dst="2" />
<file name="steering-wheel.svg" server="ftp.mustersite.ch/httpdocs/clone/" local="131782817100542192" remote="131782032000000000" Dst="2" />
<file name="strategy03.svg" server="ftp.mustersite.ch/httpdocs/clone/" local="131782817101166962" remote="131782032000000000" Dst="2" />
<file name="strategy1.svg" server="ftp.mustersite.ch/httpdocs/clone/" local="131782817102886013" remote="131782032000000000" Dst="2" />
<file name="strategy2.svg" server="ftp.mustersite.ch/httpdocs/clone/" local="131782817103354792" remote="131782032000000000" Dst="2" />
<file name="support-person.svg" server="ftp.mustersite.ch/httpdocs/clone/" local="131782817105229881" remote="131782032000000000" Dst="2" />
<file name="tablet-article.svg" server="ftp.mustersite.ch/httpdocs/clone/" local="131782817105542170" remote="131782032000000000" Dst="2" />
<file name="tablet-chart.svg" server="ftp.mustersite.ch/httpdocs/clone/" local="131782817107573446" remote="131782032000000000" Dst="2" />
<file name="tablet-chart2.svg" server="ftp.mustersite.ch/httpdocs/clone/" local="131782817107886226" remote="131782032000000000" Dst="2" />
<file name="tablet-chart3.svg" server="ftp.mustersite.ch/httpdocs/clone/" local="131782817114136420" remote="131782032000000000" Dst="2" />
<file name="tablet-pie-chart.svg" server="ftp.mustersite.ch/httpdocs/clone/" local="131782817115855266" remote="131782032000000000" Dst="2" />
<file name="tablet-pie-chart2.svg" server="ftp.mustersite.ch/httpdocs/clone/" local="131782817116323990" remote="131782032000000000" Dst="2" />
<file name="tablet.svg" server="ftp.mustersite.ch/httpdocs/clone/" local="131782817118198793" remote="131782032000000000" Dst="2" />
<file name="target.svg" server="ftp.mustersite.ch/httpdocs/clone/" local="131782817118511577" remote="131782032000000000" Dst="2" />
<file name="team.svg" server="ftp.mustersite.ch/httpdocs/clone/" local="131782817120386670" remote="131782032000000000" Dst="2" />
<file name="telescope.svg" server="ftp.mustersite.ch/httpdocs/clone/" local="131782817120855416" remote="131782032000000000" Dst="2" />
<file name="tie.svg" server="ftp.mustersite.ch/httpdocs/clone/" local="131782817122886615" remote="131782032000000000" Dst="2" />
<file name="tools.svg" server="ftp.mustersite.ch/httpdocs/clone/" local="131782817123199279" remote="131782032000000000" Dst="2" />
<file name="tools2.svg" server="ftp.mustersite.ch/httpdocs/clone/" local="131782817125074039" remote="131782032000000000" Dst="2" />
<file name="trash-bin.svg" server="ftp.mustersite.ch/httpdocs/clone/" local="131782817125543088" remote="131782032000000000" Dst="2" />
<file name="umbrella.svg" server="ftp.mustersite.ch/httpdocs/clone/" local="131782817127418151" remote="131782032000000000" Dst="2" />
<file name="user01.svg" server="ftp.mustersite.ch/httpdocs/clone/" local="131782817127886909" remote="131782032000000000" Dst="2" />
<file name="user02.svg" server="ftp.mustersite.ch/httpdocs/clone/" local="131782817129918240" remote="131782032000000000" Dst="2" />
<file name="user03.svg" server="ftp.mustersite.ch/httpdocs/clone/" local="131782817130230743" remote="131782032000000000" Dst="2" />
<file name="user04.svg" server="ftp.mustersite.ch/httpdocs/clone/" local="131782817132262100" remote="131782032000000000" Dst="2" />
<file name="user05.svg" server="ftp.mustersite.ch/httpdocs/clone/" local="131782817133824630" remote="131782032000000000" Dst="2" />
<file name="user06.svg" server="ftp.mustersite.ch/httpdocs/clone/" local="131782817134293662" remote="131782032000000000" Dst="2" />
<file name="user07.svg" server="ftp.mustersite.ch/httpdocs/clone/" local="131782817136168221" remote="131782032000000000" Dst="2" />
<file name="user08.svg" server="ftp.mustersite.ch/httpdocs/clone/" local="131782817136637219" remote="131782032000000000" Dst="2" />
<file name="user09.svg" server="ftp.mustersite.ch/httpdocs/clone/" local="131782817138824844" remote="131782032000000000" Dst="2" />
<file name="users.svg" server="ftp.mustersite.ch/httpdocs/clone/" local="131782817139137338" remote="131782032000000000" Dst="2" />
<file name="venn-diagram.svg" server="ftp.mustersite.ch/httpdocs/clone/" local="131782817141168669" remote="131782032000000000" Dst="2" />
<file name="wallet.svg" server="ftp.mustersite.ch/httpdocs/clone/" local="131782817141481168" remote="131782032000000000" Dst="2" />
<file name="wrench.svg" server="ftp.mustersite.ch/httpdocs/clone/" local="131782817143825343" remote="131782032000000000" Dst="2" />
<file name="yen.svg" server="ftp.mustersite.ch/httpdocs/clone/" local="131782817144294033" remote="131782032000000000" Dst="2" />
<file name="yinyang.svg" server="ftp.mustersite.ch/httpdocs/clone/" local="131782817147575234" remote="131782032000000000" Dst="2" />
</dwsync>